Workbook

Sheet Outreach Queue
A1: Dali marketplace outreach queue
A2: 32 source-backed targets. Wave 1 originally planned 24 proposals; one Batch A listing was verified closed, leaving 23 currently sendable. This is a presale learning wave, not a causal test of landing-page lift.
A3: Editable cells are pale yellow. Priority, Send Batch, live check, gross margin, and Data Check are system-driven. Landing links contain only an opaque marketplace reference; no-link diagnostic rows must not receive a page URL. In Vercel Analytics, ref=uw-ID maps to /_ref/upwork-ID and ref=fl-ID maps to /_ref/fl-ID. Mark Page View Yes only after that path appears. Recheck every listing in-platform before sending. Do not begin work until the selected blueprint or pilot milestone is accepted and funded.
A5: Wave | B5: Wave Variant | C5: Stage | D5: Group | E5: Priority | F5: Record Key | G5: Match Score | H5: Platform | I5: Title | J5: Budget | K5: Competition | L5: Posted | M5: Observed Pain | N5: Pilot Boundary | O5: Copy-ready Outreach Message | P5: Tracking Landing URL | Q5: Listing URL | R5: Confidence / Red Flag | S5: Sent Date | T5: Page View | U5: Reply Date | V5: Objection | W5: Notes | X5: Qualification | Y5: Sales Path | Z5: Quoted Amount | AA5: Funded Amount | AB5: Archive Reason | AC5: Delivery Hours | AD5: Direct Cost | AE5: Gross Margin % | AF5: Next Follow-up | AG5: Send Batch | AH5: Live Check | AI5: Live Check Note | AJ5: Checked At | AK5: Data Check
A6: Wave 1 | B6: Landing Link | C6: Not Sent | D6: Lead Response | E6: =IF(G6>=90,"A",IF(G6>=80,"B",IF(G6>=70,"C","D"))) | F6: Upwork:~022079500683280398086 | G6: 95 | H6: Upwork | I6: Agentic AI Automation Engineer | J6: Hourly: $40.00 - $75.00 | K6: 50+ | L6: last week | M6: Manual lead intake, CRM updates, and follow-up need to become a reliable agentic process that extracts, classifies, updates CRM, sends a summary, and escalates uncertain cases. | N6: One lead source cluster, one first-reply playbook, one CRM or calendar action path, and visible human approval; exclude outbound prospecting and autonomous pricing. | O6: You want manual lead intake, CRM updates, and follow-up turned into a reliable agentic process with extraction, classification, summaries, and human handoff. We already have a production-ready product core for this at Dali Agency (lead-response core): intake → extract/classify → CRM or calendar action → draft or first reply → human approval on uncertain/pricing cases. We are not starting from a blank repo. The paid work is customization under your stack: your lead sources, CRM fields, qualification rules, and which cases must always stop for a person. First customization pilot I would lock: one lead source cluster, one first-reply playbook, one CRM/calendar action, visible approval on uncertain cases. Packaged boundary + how we run that pilot: https://dali.agents.ge/for/upwork/lead-response?ref=uw-022079500683280398086 If that matches, reply here in Upwork with primary intake channel, CRM, and the lead classes that must always wait for a person. I will confirm fit and send a fixed pilot milestone (or a short paid blueprint if scope is still loose) before any implementation starts. | P6: https://dali.agents.ge/for/upwork/lead-response?ref=uw-022079500683280398086 | Q6: https://www.upwork.com/jobs/span-class-highlight-Agentic-span-span-class-highlight-span-span-class-highlight-Automation-span-Engineer_~022079500683280398086/?referrer_url_path=/nx/search/jobs/ | R6: High confidence; 50+ proposals and a mismatch between metadata hours and description hours. | T6: Unknown | X6: Not Evaluated | Y6: Unassigned | AE6: =IFERROR((AA6-AD6)/AA6,"") | AG6: Batch B | AH6: Manual Check | AI6: Anonymous direct page was blocked by a Cloudflare challenge. Verify open status and scope inside Upwork. | AJ6: 2026-07-30 03:13 +04 | AK6: =IF(AND(U6<>"",S6=""),"WARN: Reply date without sent date",IF(AND(OR(C6="Sent",C6="Replied",C6="Qualified",C6="Blueprint Proposed",C6="Pilot Proposed",C6="Blueprint Funded",C6="Pilot Funded",C6="Won"),S6=""),"WARN: Stage requires sent date",IF(AND(OR(C6="Replied",C6="Qualified",C6="Blueprint Proposed",C6="Pilot Proposed",C6="Blueprint Funded",C6="Pilot Funded",C6="Won"),U6=""),"WARN: Stage requires reply date",IF(AND(X6="Qualified",U6=""),"WARN: Qualified without reply date",IF(AND(C6="Qualified",X6<>"Qualified"),"WARN: Qualified stage mismatch",IF(AND(X6="Qualified",NOT(OR(C6="Qualified",C6="Blueprint Proposed",C6="Pilot Proposed",C6="Blueprint Funded",C6="Pilot Funded",C6="Won"))),"WARN: Qualified value stage mismatch",IF(AND(Z6>0,NOT(OR(Y6="Blueprint",Y6="Direct Pilot"))),"WARN: Quote without sales path",IF(AND(OR(C6="Blueprint Proposed",C6="Blueprint Funded"),Y6<>"Blueprint"),"WARN: Blueprint stage path mismatch",IF(AND(OR(C6="Pilot Proposed",C6="Pilot Funded"),Y6<>"Direct Pilot"),"WARN: Pilot stage path mismatch",IF(AND(OR(C6="Blueprint Proposed",C6="Pilot Proposed",C6="Blueprint Funded",C6="Pilot Funded",C6="Won"),Z6<=0),"WARN: Offer stage without quote",IF(AND(Z6>0,NOT(OR(C6="Blueprint Proposed",C6="Pilot Proposed",C6="Blueprint Funded",C6="Pilot Funded",C6="Won"))),"WARN: Quote stage mismatch",IF(AND(AA6>0,Z6<=0),"WARN: Funded without quote",IF(AND(OR(C6="Blueprint Funded",C6="Pilot Funded",C6="Won"),AA6<=0),"WARN: Funded stage without amount",IF(AND(AA6>0,NOT(OR(C6="Blueprint Funded",C6="Pilot Funded",C6="Won"))),"WARN: Funded value stage mismatch","OK"))))))))))))))
A7: Wave 1 | B7: Landing Link | C7: Not Sent | D7: Lead Response | E7: =IF(G7>=90,"A",IF(G7>=80,"B",IF(G7>=70,"C","D"))) | F7: Upwork:~022082094672185738150 | G7: 95 | H7: Upwork | I7: AI Agent / CRM System Setup | J7: Hourly: $22-$29 | K7: 50+ | L7: 4 hours ago | M7: Follow-up across Gmail, Monday, and Slack must keep replies, history, next contact, reminders, summaries, and drafts in sync while blocking duplicates and do-not-contact contacts. | N7: One inbound communication flow, one history store, one next-contact rule, and one reminder or draft output; exclude broader CRM redesign. | O7: Your brief is follow-up automation across Gmail, Monday, and Slack: reply tracking, next-contact history, reminders, and draft emails without duplicates or do-not-contact misses. We already have a production-ready product core for this at Dali Agency (lead-response core): intake → extract/classify → CRM or calendar action → draft or first reply → human approval on uncertain/pricing cases. We are not starting from a blank repo. The paid work is customization under your stack: your lead sources, CRM fields, qualification rules, and which cases must always stop for a person. First customization pilot I would lock: one inbound communication flow, one history store, one next-contact rule, and one reminder or draft path with human approval on sensitive sends. Packaged boundary + how we run that pilot: https://dali.agents.ge/for/upwork/lead-response?ref=uw-022082094672185738150 If that matches, reply here in Upwork with primary intake channel, CRM, and the lead classes that must always wait for a person. I will confirm fit and send a fixed pilot milestone (or a short paid blueprint if scope is still loose) before any implementation starts. | P7: https://dali.agents.ge/for/upwork/lead-response?ref=uw-022082094672185738150 | Q7: https://www.upwork.com/jobs/Agent-CRM-System-Setup_~022082094672185738150/?referrer_url_path=find_work_home | R7: High confidence; integrations and API permissions are not pinned down, with 50+ proposals and a low rate. | T7: Unknown | X7: Not Evaluated | Y7: Unassigned | AE7: =IFERROR((AA7-AD7)/AA7,"") | AG7: Batch A | AH7: Manual Check | AI7: Anonymous Upwork view exposed a private-listing status but not the brief. Confirm inside the working account; skip if it remains private. | AJ7: 2026-07-30 03:15 +04 | AK7: =IF(AND(U7<>"",S7=""),"WARN: Reply date without sent date",IF(AND(OR(C7="Sent",C7="Replied",C7="Qualified",C7="Blueprint Proposed",C7="Pilot Proposed",C7="Blueprint Funded",C7="Pilot Funded",C7="Won"),S7=""),"WARN: Stage requires sent date",IF(AND(OR(C7="Replied",C7="Qualified",C7="Blueprint Proposed",C7="Pilot Proposed",C7="Blueprint Funded",C7="Pilot Funded",C7="Won"),U7=""),"WARN: Stage requires reply date",IF(AND(X7="Qualified",U7=""),"WARN: Qualified without reply date",IF(AND(C7="Qualified",X7<>"Qualified"),"WARN: Qualified stage mismatch",IF(AND(X7="Qualified",NOT(OR(C7="Qualified",C7="Blueprint Proposed",C7="Pilot Proposed",C7="Blueprint Funded",C7="Pilot Funded",C7="Won"))),"WARN: Qualified value stage mismatch",IF(AND(Z7>0,NOT(OR(Y7="Blueprint",Y7="Direct Pilot"))),"WARN: Quote without sales path",IF(AND(OR(C7="Blueprint Proposed",C7="Blueprint Funded"),Y7<>"Blueprint"),"WARN: Blueprint stage path mismatch",IF(AND(OR(C7="Pilot Proposed",C7="Pilot Funded"),Y7<>"Direct Pilot"),"WARN: Pilot stage path mismatch",IF(AND(OR(C7="Blueprint Proposed",C7="Pilot Proposed",C7="Blueprint Funded",C7="Pilot Funded",C7="Won"),Z7<=0),"WARN: Offer stage without quote",IF(AND(Z7>0,NOT(OR(C7="Blueprint Proposed",C7="Pilot Proposed",C7="Blueprint Funded",C7="Pilot Funded",C7="Won"))),"WARN: Quote stage mismatch",IF(AND(AA7>0,Z7<=0),"WARN: Funded without quote",IF(AND(OR(C7="Blueprint Funded",C7="Pilot Funded",C7="Won"),AA7<=0),"WARN: Funded stage without amount",IF(AND(AA7>0,NOT(OR(C7="Blueprint Funded",C7="Pilot Funded",C7="Won"))),"WARN: Funded value stage mismatch","OK"))))))))))))))
A8: Wave 1 | B8: Landing Link | C8: Not Sent | D8: Lead Response | E8: =IF(G8>=90,"A",IF(G8>=80,"B",IF(G8>=70,"C","D"))) | F8: Upwork:~022080272851686168921 | G8: 90 | H8: Upwork | I8: AI Agent Developer for Field Service Operations Automation | J8: $550.00 | K8: 50+ | L8: 5 days ago | M8: Field service operations need an agent to read email and forms, classify urgency and location, update CRM, select time and specialist, draft replies, remind, and escalate risk. | N8: One intake path to one CRM update and one scheduling or review path, with approval and audit logs. | O8: Field service ops need an agent that reads email/forms, classifies urgency and location, updates CRM, schedules, drafts replies, and escalates risk. We already have a production-ready product core for this at Dali Agency (lead-response core): intake → extract/classify → CRM or calendar action → draft or first reply → human approval on uncertain/pricing cases. We are not starting from a blank repo. The paid work is customization under your stack: your lead sources, CRM fields, qualification rules, and which cases must always stop for a person. First customization pilot I would lock: one intake path → one CRM update → one scheduling/review path with approval and audit logs. Packaged boundary + how we run that pilot: https://dali.agents.ge/for/upwork/lead-response?ref=uw-022080272851686168921 If that matches, reply here in Upwork with primary intake channel, CRM, and the lead classes that must always wait for a person. I will confirm fit and send a fixed pilot milestone (or a short paid blueprint if scope is still loose) before any implementation starts. | P8: https://dali.agents.ge/for/upwork/lead-response?ref=uw-022080272851686168921 | Q8: https://www.upwork.com/jobs/span-class-highlight-span-span-class-highlight-Agent-span-Developer-for-Field-Service-Operations-span-class-highlight-Automation-span_~022080272851686168921/?referrer_url_path=/nx/search/jobs/ | R8: High confidence; a low fixed budget for Phase 1 and 50+ applicants. | T8: Unknown | X8: Not Evaluated | Y8: Unassigned | AE8: =IFERROR((AA8-AD8)/AA8,"") | AG8: Batch B | AH8: Manual Check | AI8: Anonymous direct page was blocked by a Cloudflare challenge. Verify open status and scope inside Upwork. | AJ8: 2026-07-30 03:13 +04 | AK8: =IF(AND(U8<>"",S8=""),"WARN: Reply date without sent date",IF(AND(OR(C8="Sent",C8="Replied",C8="Qualified",C8="Blueprint Proposed",C8="Pilot Proposed",C8="Blueprint Funded",C8="Pilot Funded",C8="Won"),S8=""),"WARN: Stage requires sent date",IF(AND(OR(C8="Replied",C8="Qualified",C8="Blueprint Proposed",C8="Pilot Proposed",C8="Blueprint Funded",C8="Pilot Funded",C8="Won"),U8=""),"WARN: Stage requires reply date",IF(AND(X8="Qualified",U8=""),"WARN: Qualified without reply date",IF(AND(C8="Qualified",X8<>"Qualified"),"WARN: Qualified stage mismatch",IF(AND(X8="Qualified",NOT(OR(C8="Qualified",C8="Blueprint Proposed",C8="Pilot Proposed",C8="Blueprint Funded",C8="Pilot Funded",C8="Won"))),"WARN: Qualified value stage mismatch",IF(AND(Z8>0,NOT(OR(Y8="Blueprint",Y8="Direct Pilot"))),"WARN: Quote without sales path",IF(AND(OR(C8="Blueprint Proposed",C8="Blueprint Funded"),Y8<>"Blueprint"),"WARN: Blueprint stage path mismatch",IF(AND(OR(C8="Pilot Proposed",C8="Pilot Funded"),Y8<>"Direct Pilot"),"WARN: Pilot stage path mismatch",IF(AND(OR(C8="Blueprint Proposed",C8="Pilot Proposed",C8="Blueprint Funded",C8="Pilot Funded",C8="Won"),Z8<=0),"WARN: Offer stage without quote",IF(AND(Z8>0,NOT(OR(C8="Blueprint Proposed",C8="Pilot Proposed",C8="Blueprint Funded",C8="Pilot Funded",C8="Won"))),"WARN: Quote stage mismatch",IF(AND(AA8>0,Z8<=0),"WARN: Funded without quote",IF(AND(OR(C8="Blueprint Funded",C8="Pilot Funded",C8="Won"),AA8<=0),"WARN: Funded stage without amount",IF(AND(AA8>0,NOT(OR(C8="Blueprint Funded",C8="Pilot Funded",C8="Won"))),"WARN: Funded value stage mismatch","OK"))))))))))))))
A9: Wave 1 | B9: Landing Link | C9: Not Sent | D9: Lead Response | E9: =IF(G9>=90,"A",IF(G9>=80,"B",IF(G9>=70,"C","D"))) | F9: Upwork:~022076935615291863294 | G9: 90 | H9: Upwork | I9: Ai Automation for marketing agency | J9: $900.00 | K9: 50+ | L9: 2 weeks ago | M9: A marketing agency wants AI tied into CRM, email, and project management to qualify leads, support bookings, prepare proposals, and handle handoffs. | N9: One workflow, preferably lead qualification or support handoff, with one acceptance test and expansion only after validation. | O9: Your agency wants AI tied into CRM, email, and PM for lead qualification, bookings, proposals, and handoffs - starting small is the right call. We already have a production-ready product core for this at Dali Agency (lead-response core): intake → extract/classify → CRM or calendar action → draft or first reply → human approval on uncertain/pricing cases. We are not starting from a blank repo. The paid work is customization under your stack: your lead sources, CRM fields, qualification rules, and which cases must always stop for a person. First customization pilot I would lock: one CRM-connected pilot workflow, one acceptance test, one handoff path before proposals or wider automation. Packaged boundary + how we run that pilot: https://dali.agents.ge/for/upwork/lead-response?ref=uw-022076935615291863294 If that matches, reply here in Upwork with primary intake channel, CRM, and the lead classes that must always wait for a person. I will confirm fit and send a fixed pilot milestone (or a short paid blueprint if scope is still loose) before any implementation starts. | P9: https://dali.agents.ge/for/upwork/lead-response?ref=uw-022076935615291863294 | Q9: https://www.upwork.com/jobs/span-class-highlight-span-span-class-highlight-Automation-span-for-marketing-agency_~022076935615291863294/?referrer_url_path=/nx/search/jobs/ | R9: High confidence; no spend or rating yet and 50+ proposals. | T9: Unknown | X9: Not Evaluated | Y9: Unassigned | AE9: =IFERROR((AA9-AD9)/AA9,"") | AG9: Batch C | AH9: Manual Check | AI9: Anonymous direct page was blocked by a Cloudflare challenge. Verify open status and scope inside Upwork. | AJ9: 2026-07-30 03:14 +04 | AK9: =IF(AND(U9<>"",S9=""),"WARN: Reply date without sent date",IF(AND(OR(C9="Sent",C9="Replied",C9="Qualified",C9="Blueprint Proposed",C9="Pilot Proposed",C9="Blueprint Funded",C9="Pilot Funded",C9="Won"),S9=""),"WARN: Stage requires sent date",IF(AND(OR(C9="Replied",C9="Qualified",C9="Blueprint Proposed",C9="Pilot Proposed",C9="Blueprint Funded",C9="Pilot Funded",C9="Won"),U9=""),"WARN: Stage requires reply date",IF(AND(X9="Qualified",U9=""),"WARN: Qualified without reply date",IF(AND(C9="Qualified",X9<>"Qualified"),"WARN: Qualified stage mismatch",IF(AND(X9="Qualified",NOT(OR(C9="Qualified",C9="Blueprint Proposed",C9="Pilot Proposed",C9="Blueprint Funded",C9="Pilot Funded",C9="Won"))),"WARN: Qualified value stage mismatch",IF(AND(Z9>0,NOT(OR(Y9="Blueprint",Y9="Direct Pilot"))),"WARN: Quote without sales path",IF(AND(OR(C9="Blueprint Proposed",C9="Blueprint Funded"),Y9<>"Blueprint"),"WARN: Blueprint stage path mismatch",IF(AND(OR(C9="Pilot Proposed",C9="Pilot Funded"),Y9<>"Direct Pilot"),"WARN: Pilot stage path mismatch",IF(AND(OR(C9="Blueprint Proposed",C9="Pilot Proposed",C9="Blueprint Funded",C9="Pilot Funded",C9="Won"),Z9<=0),"WARN: Offer stage without quote",IF(AND(Z9>0,NOT(OR(C9="Blueprint Proposed",C9="Pilot Proposed",C9="Blueprint Funded",C9="Pilot Funded",C9="Won"))),"WARN: Quote stage mismatch",IF(AND(AA9>0,Z9<=0),"WARN: Funded without quote",IF(AND(OR(C9="Blueprint Funded",C9="Pilot Funded",C9="Won"),AA9<=0),"WARN: Funded stage without amount",IF(AND(AA9>0,NOT(OR(C9="Blueprint Funded",C9="Pilot Funded",C9="Won"))),"WARN: Funded value stage mismatch","OK"))))))))))))))
A10: Wave 1 | B10: Landing Link | C10: Not Sent | D10: Lead Response | E10: =IF(G10>=90,"A",IF(G10>=80,"B",IF(G10>=70,"C","D"))) | F10: Upwork:~022082059740997677549 | G10: 90 | H10: Upwork | I10: Senior AI Engineer to Build an AI Sales Operations Employee (LLMs, CRM, Multi-Agent AI) | J10: Hourly: $30-$45 | K10: 50+ | L10: 6 hours ago | M10: A production AI sales employee must research and qualify leads, generate outreach and proposals, update CRM, follow up, book meetings, and show analytics. | N10: One lead-research-to-CRM loop, one outreach path, one booking handoff, and monitoring. | O10: You are hiring for a production AI sales-ops employee: research/qualify, CRM, outreach, follow-up, booking, analytics. That is a platform end-state, not a day-one blank build. We already have a production-ready product core for this at Dali Agency (lead-response core): intake → extract/classify → CRM or calendar action → draft or first reply → human approval on uncertain/pricing cases. We are not starting from a blank repo. The paid work is customization under your stack: your lead sources, CRM fields, qualification rules, and which cases must always stop for a person. First customization pilot I would lock: one lead-research → qualification → CRM update → booked-meeting handoff path first, with multi-agent layers only after that path is proven. Packaged boundary + how we run that pilot: https://dali.agents.ge/for/upwork/lead-response?ref=uw-022082059740997677549 If that matches, reply here in Upwork with primary intake channel, CRM, and the lead classes that must always wait for a person. I will confirm fit and send a fixed pilot milestone (or a short paid blueprint if scope is still loose) before any implementation starts. | P10: https://dali.agents.ge/for/upwork/lead-response?ref=uw-022082059740997677549 | Q10: https://www.upwork.com/jobs/Senior-Engineer-Build-Sales-Operations-Employee-LLMs-CRM-Multi-Agent_~022082059740997677549/?referrer_url_path=find_work_home | R10: High confidence; large production scope, 3-6 months, 30+ hours per week, and 50+ proposals. | T10: Unknown | X10: Not Evaluated | Y10: Unassigned | AE10: =IFERROR((AA10-AD10)/AA10,"") | AG10: Batch A | AH10: Open | AI10: Full card accessible and scope matched. 50+ proposals and client viewed yesterday. | AJ10: 2026-07-30 03:16 +04 | AK10: =IF(AND(U10<>"",S10=""),"WARN: Reply date without sent date",IF(AND(OR(C10="Sent",C10="Replied",C10="Qualified",C10="Blueprint Proposed",C10="Pilot Proposed",C10="Blueprint Funded",C10="Pilot Funded",C10="Won"),S10=""),"WARN: Stage requires sent date",IF(AND(OR(C10="Replied",C10="Qualified",C10="Blueprint Proposed",C10="Pilot Proposed",C10="Blueprint Funded",C10="Pilot Funded",C10="Won"),U10=""),"WARN: Stage requires reply date",IF(AND(X10="Qualified",U10=""),"WARN: Qualified without reply date",IF(AND(C10="Qualified",X10<>"Qualified"),"WARN: Qualified stage mismatch",IF(AND(X10="Qualified",NOT(OR(C10="Qualified",C10="Blueprint Proposed",C10="Pilot Proposed",C10="Blueprint Funded",C10="Pilot Funded",C10="Won"))),"WARN: Qualified value stage mismatch",IF(AND(Z10>0,NOT(OR(Y10="Blueprint",Y10="Direct Pilot"))),"WARN: Quote without sales path",IF(AND(OR(C10="Blueprint Proposed",C10="Blueprint Funded"),Y10<>"Blueprint"),"WARN: Blueprint stage path mismatch",IF(AND(OR(C10="Pilot Proposed",C10="Pilot Funded"),Y10<>"Direct Pilot"),"WARN: Pilot stage path mismatch",IF(AND(OR(C10="Blueprint Proposed",C10="Pilot Proposed",C10="Blueprint Funded",C10="Pilot Funded",C10="Won"),Z10<=0),"WARN: Offer stage without quote",IF(AND(Z10>0,NOT(OR(C10="Blueprint Proposed",C10="Pilot Proposed",C10="Blueprint Funded",C10="Pilot Funded",C10="Won"))),"WARN: Quote stage mismatch",IF(AND(AA10>0,Z10<=0),"WARN: Funded without quote",IF(AND(OR(C10="Blueprint Funded",C10="Pilot Funded",C10="Won"),AA10<=0),"WARN: Funded stage without amount",IF(AND(AA10>0,NOT(OR(C10="Blueprint Funded",C10="Pilot Funded",C10="Won"))),"WARN: Funded value stage mismatch","OK"))))))))))))))
A11: Wave 1 | B11: Landing Link | C11: Not Sent | D11: Lead Response | E11: =IF(G11>=90,"A",IF(G11>=80,"B",IF(G11>=70,"C","D"))) | F11: Upwork:~022081957032774069874 | G11: 90 | H11: Upwork | I11: AI Automation Developer - Gmail, OpenAI & SMS | J11: Hourly: $15-$35 | K11: 50+ | L11: 13 hours ago | M11: A leasing assistant must read new applications, answer by email and SMS, pre-screen tenants, schedule showings, and log communications. | N11: One leasing workflow: email intake, standard replies, pre-screening, calendar booking, and human review for sensitive decisions. | O11: The leasing assistant brief is email/SMS intake, standard replies, pre-screen, showing booking, and communication log. We already have a production-ready product core for this at Dali Agency (lead-response core): intake → extract/classify → CRM or calendar action → draft or first reply → human approval on uncertain/pricing cases. We are not starting from a blank repo. The paid work is customization under your stack: your lead sources, CRM fields, qualification rules, and which cases must always stop for a person. First customization pilot I would lock: one application flow, one calendar path, human review for any sensitive tenant decision. Packaged boundary + how we run that pilot: https://dali.agents.ge/for/upwork/lead-response?ref=uw-022081957032774069874 If that matches, reply here in Upwork with primary intake channel, CRM, and the lead classes that must always wait for a person. I will confirm fit and send a fixed pilot milestone (or a short paid blueprint if scope is still loose) before any implementation starts. | P11: https://dali.agents.ge/for/upwork/lead-response?ref=uw-022081957032774069874 | Q11: https://www.upwork.com/jobs/Automation-Developer-Gmail-OpenAI-SMS_~022081957032774069874/?referrer_url_path=find_work_home | R11: High confidence; privacy-sensitive tenant screening and 50+ proposals. | T11: Unknown | X11: Not Evaluated | Y11: Unassigned | AE11: =IFERROR((AA11-AD11)/AA11,"") | AG11: Batch B | AH11: Manual Check | AI11: Anonymous direct page was blocked by a Cloudflare challenge. Verify open status and scope inside Upwork. | AJ11: 2026-07-30 03:13 +04 | AK11: =IF(AND(U11<>"",S11=""),"WARN: Reply date without sent date",IF(AND(OR(C11="Sent",C11="Replied",C11="Qualified",C11="Blueprint Proposed",C11="Pilot Proposed",C11="Blueprint Funded",C11="Pilot Funded",C11="Won"),S11=""),"WARN: Stage requires sent date",IF(AND(OR(C11="Replied",C11="Qualified",C11="Blueprint Proposed",C11="Pilot Proposed",C11="Blueprint Funded",C11="Pilot Funded",C11="Won"),U11=""),"WARN: Stage requires reply date",IF(AND(X11="Qualified",U11=""),"WARN: Qualified without reply date",IF(AND(C11="Qualified",X11<>"Qualified"),"WARN: Qualified stage mismatch",IF(AND(X11="Qualified",NOT(OR(C11="Qualified",C11="Blueprint Proposed",C11="Pilot Proposed",C11="Blueprint Funded",C11="Pilot Funded",C11="Won"))),"WARN: Qualified value stage mismatch",IF(AND(Z11>0,NOT(OR(Y11="Blueprint",Y11="Direct Pilot"))),"WARN: Quote without sales path",IF(AND(OR(C11="Blueprint Proposed",C11="Blueprint Funded"),Y11<>"Blueprint"),"WARN: Blueprint stage path mismatch",IF(AND(OR(C11="Pilot Proposed",C11="Pilot Funded"),Y11<>"Direct Pilot"),"WARN: Pilot stage path mismatch",IF(AND(OR(C11="Blueprint Proposed",C11="Pilot Proposed",C11="Blueprint Funded",C11="Pilot Funded",C11="Won"),Z11<=0),"WARN: Offer stage without quote",IF(AND(Z11>0,NOT(OR(C11="Blueprint Proposed",C11="Pilot Proposed",C11="Blueprint Funded",C11="Pilot Funded",C11="Won"))),"WARN: Quote stage mismatch",IF(AND(AA11>0,Z11<=0),"WARN: Funded without quote",IF(AND(OR(C11="Blueprint Funded",C11="Pilot Funded",C11="Won"),AA11<=0),"WARN: Funded stage without amount",IF(AND(AA11>0,NOT(OR(C11="Blueprint Funded",C11="Pilot Funded",C11="Won"))),"WARN: Funded value stage mismatch","OK"))))))))))))))
A12: Wave 1 | B12: Landing Link | C12: Not Sent | D12: Lead Response | E12: =IF(G12>=90,"A",IF(G12>=80,"B",IF(G12>=70,"C","D"))) | F12: Upwork:~022071869598491167955 | G12: 90 | H12: Upwork | I12: AI Automation Specialist for Lead Qualification, CRM Routing and Multichannel Appointment Booking | J12: $500.00 | K12: 20 to 50 | L12: 4 weeks ago | M12: A multilingual appointment system must classify messages, manage booking changes, reminders, and waitlists, sync calendar and CRM, and escalate when needed. | N12: One language, one appointment flow, one CRM and calendar integration, and explicit escalation rules. | O12: You need multilingual lead qualification, CRM routing, and multichannel appointment booking with reschedules, reminders, and waitlists. We already have a production-ready product core for this at Dali Agency (lead-response core): intake → extract/classify → CRM or calendar action → draft or first reply → human approval on uncertain/pricing cases. We are not starting from a blank repo. The paid work is customization under your stack: your lead sources, CRM fields, qualification rules, and which cases must always stop for a person. First customization pilot I would lock: one language first, one appointment flow, one CRM+calendar integration, explicit escalation rules. Packaged boundary + how we run that pilot: https://dali.agents.ge/for/upwork/lead-response?ref=uw-022071869598491167955 If that matches, reply here in Upwork with primary intake channel, CRM, and the lead classes that must always wait for a person. I will confirm fit and send a fixed pilot milestone (or a short paid blueprint if scope is still loose) before any implementation starts. | P12: https://dali.agents.ge/for/upwork/lead-response?ref=uw-022071869598491167955 | Q12: https://www.upwork.com/jobs/span-class-highlight-span-span-class-highlight-Automation-span-Specialist-for-Lead-Qualification-CRM-Routing-and-Multichannel-Appointment-Booking_~022071869598491167955/?referrer_url_path=/nx/search/jobs/ | R12: High confidence; the fixed $500 scope is too small for a multi-stage system. | T12: Unknown | X12: Not Evaluated | Y12: Unassigned | AE12: =IFERROR((AA12-AD12)/AA12,"") | AG12: Batch C | AH12: Manual Check | AI12: Anonymous direct page was blocked by a Cloudflare challenge. Verify open status and scope inside Upwork. | AJ12: 2026-07-30 03:14 +04 | AK12: =IF(AND(U12<>"",S12=""),"WARN: Reply date without sent date",IF(AND(OR(C12="Sent",C12="Replied",C12="Qualified",C12="Blueprint Proposed",C12="Pilot Proposed",C12="Blueprint Funded",C12="Pilot Funded",C12="Won"),S12=""),"WARN: Stage requires sent date",IF(AND(OR(C12="Replied",C12="Qualified",C12="Blueprint Proposed",C12="Pilot Proposed",C12="Blueprint Funded",C12="Pilot Funded",C12="Won"),U12=""),"WARN: Stage requires reply date",IF(AND(X12="Qualified",U12=""),"WARN: Qualified without reply date",IF(AND(C12="Qualified",X12<>"Qualified"),"WARN: Qualified stage mismatch",IF(AND(X12="Qualified",NOT(OR(C12="Qualified",C12="Blueprint Proposed",C12="Pilot Proposed",C12="Blueprint Funded",C12="Pilot Funded",C12="Won"))),"WARN: Qualified value stage mismatch",IF(AND(Z12>0,NOT(OR(Y12="Blueprint",Y12="Direct Pilot"))),"WARN: Quote without sales path",IF(AND(OR(C12="Blueprint Proposed",C12="Blueprint Funded"),Y12<>"Blueprint"),"WARN: Blueprint stage path mismatch",IF(AND(OR(C12="Pilot Proposed",C12="Pilot Funded"),Y12<>"Direct Pilot"),"WARN: Pilot stage path mismatch",IF(AND(OR(C12="Blueprint Proposed",C12="Pilot Proposed",C12="Blueprint Funded",C12="Pilot Funded",C12="Won"),Z12<=0),"WARN: Offer stage without quote",IF(AND(Z12>0,NOT(OR(C12="Blueprint Proposed",C12="Pilot Proposed",C12="Blueprint Funded",C12="Pilot Funded",C12="Won"))),"WARN: Quote stage mismatch",IF(AND(AA12>0,Z12<=0),"WARN: Funded without quote",IF(AND(OR(C12="Blueprint Funded",C12="Pilot Funded",C12="Won"),AA12<=0),"WARN: Funded stage without amount",IF(AND(AA12>0,NOT(OR(C12="Blueprint Funded",C12="Pilot Funded",C12="Won"))),"WARN: Funded value stage mismatch","OK"))))))))))))))
A13: Wave 1 | B13: No-Link Diagnostic | C13: Not Sent | D13: Lead Response | E13: =IF(G13>=90,"A",IF(G13>=80,"B",IF(G13>=70,"C","D"))) | F13: Upwork:~022082076899341845245 | G13: 85 | H13: Upwork | I13: Full Stack AI Automation Engineer Ai Sales Workflow Platform | J13: Hourly: $25-$47 | K13: 50+ | L13: 5 hours ago | M13: A high-volume service business needs an AI sales agent that qualifies leads, updates GoHighLevel, assigns a manager, follows up, books meetings, and prepares call summaries. | N13: One lead source to one CRM action path, booking handoff, and pre-call summary. | O13: You already have a clear sales-ops workflow: qualify, update GoHighLevel, assign the manager, follow up, and book meetings. We already have a production-ready product core for this at Dali Agency (lead-response core): intake → extract/classify → CRM or calendar action → draft or first reply → human approval on uncertain/pricing cases. We are not starting from a blank repo. The paid work is customization under your stack: your lead sources, CRM fields, qualification rules, and which cases must always stop for a person. First customization pilot I would lock: one lead source, one GoHighLevel action path, one manager assignment rule, and human approval on edge cases. If that matches, reply here in Upwork with primary intake channel, CRM, and the lead classes that must always wait for a person. I will confirm fit and send a fixed pilot milestone (or a short paid blueprint if scope is still loose) before any implementation starts. | P13: No link in diagnostic proposal | Q13: https://www.upwork.com/jobs/Full-Stack-Automation-Engineer-Sales-Workflow-Platform_~022082076899341845245/?referrer_url_path=find_work_home | R13: High confidence; 3-6 month scope, 50+ proposals, and no proven payment history. | T13: Unknown | X13: Not Evaluated | Y13: Unassigned | AE13: =IFERROR((AA13-AD13)/AA13,"") | AG13: Batch A | AH13: Open | AI13: Full card accessible and scope matched. 50+ proposals, client viewed yesterday, one interview. | AJ13: 2026-07-30 03:15 +04 | AK13: =IF(AND(U13<>"",S13=""),"WARN: Reply date without sent date",IF(AND(OR(C13="Sent",C13="Replied",C13="Qualified",C13="Blueprint Proposed",C13="Pilot Proposed",C13="Blueprint Funded",C13="Pilot Funded",C13="Won"),S13=""),"WARN: Stage requires sent date",IF(AND(OR(C13="Replied",C13="Qualified",C13="Blueprint Proposed",C13="Pilot Proposed",C13="Blueprint Funded",C13="Pilot Funded",C13="Won"),U13=""),"WARN: Stage requires reply date",IF(AND(X13="Qualified",U13=""),"WARN: Qualified without reply date",IF(AND(C13="Qualified",X13<>"Qualified"),"WARN: Qualified stage mismatch",IF(AND(X13="Qualified",NOT(OR(C13="Qualified",C13="Blueprint Proposed",C13="Pilot Proposed",C13="Blueprint Funded",C13="Pilot Funded",C13="Won"))),"WARN: Qualified value stage mismatch",IF(AND(Z13>0,NOT(OR(Y13="Blueprint",Y13="Direct Pilot"))),"WARN: Quote without sales path",IF(AND(OR(C13="Blueprint Proposed",C13="Blueprint Funded"),Y13<>"Blueprint"),"WARN: Blueprint stage path mismatch",IF(AND(OR(C13="Pilot Proposed",C13="Pilot Funded"),Y13<>"Direct Pilot"),"WARN: Pilot stage path mismatch",IF(AND(OR(C13="Blueprint Proposed",C13="Pilot Proposed",C13="Blueprint Funded",C13="Pilot Funded",C13="Won"),Z13<=0),"WARN: Offer stage without quote",IF(AND(Z13>0,NOT(OR(C13="Blueprint Proposed",C13="Pilot Proposed",C13="Blueprint Funded",C13="Pilot Funded",C13="Won"))),"WARN: Quote stage mismatch",IF(AND(AA13>0,Z13<=0),"WARN: Funded without quote",IF(AND(OR(C13="Blueprint Funded",C13="Pilot Funded",C13="Won"),AA13<=0),"WARN: Funded stage without amount",IF(AND(AA13>0,NOT(OR(C13="Blueprint Funded",C13="Pilot Funded",C13="Won"))),"WARN: Funded value stage mismatch","OK"))))))))))))))
A14: Hold | B14: Hold | C14: Hold | D14: Lead Response | E14: =IF(G14>=90,"A",IF(G14>=80,"B",IF(G14>=70,"C","D"))) | F14: Upwork:~022082023362208208284 | G14: 85 | H14: Upwork | I14: AI Agent & n8n Automation System for Freight Forwarding Company | J14: Hourly | K14: 20 to 50 | L14: 5 hours ago | M14: Freight-forwarding leads need dedupe, CRM status updates, email sequences, and reporting before later freight calculations. | N14: One lead intake to dedupe, CRM status, one email sequence, and one report. | O14: I would ship one lead-to-follow-up path first: lead intake, dedupe, CRM status, sequence email, report. Freight calculation can wait. I packaged that exact pilot boundary here: https://dali.agents.ge/for/upwork/lead-response?ref=uw-022082023362208208284 If that boundary matches your brief, reply here in Upwork with your primary intake channel, CRM, and the lead classes that must always wait for a person. I will turn those inputs into the first replay set and pass/fail acceptance test before implementation. | P14: https://dali.agents.ge/for/upwork/lead-response?ref=uw-022082023362208208284 | Q14: https://www.upwork.com/jobs/span-class-highlight-span-span-class-highlight-Agent-span-amp-n8n-span-class-highlight-Automation-span-System-for-Freight-Forwarding-Company_~022082023362208208284/?referrer_url_path=/nx/search/jobs/ | R14: High confidence; future RFQ and freight-calculation scope should stay outside the pilot. | T14: Unknown | X14: Not Evaluated | Y14: Hold | AE14: =IFERROR((AA14-AD14)/AA14,"") | AG14: Hold | AH14: Not Checked | AI14: Hold row; not part of the current live-listing audit. | AK14: =IF(AND(U14<>"",S14=""),"WARN: Reply date without sent date",IF(AND(OR(C14="Sent",C14="Replied",C14="Qualified",C14="Blueprint Proposed",C14="Pilot Proposed",C14="Blueprint Funded",C14="Pilot Funded",C14="Won"),S14=""),"WARN: Stage requires sent date",IF(AND(OR(C14="Replied",C14="Qualified",C14="Blueprint Proposed",C14="Pilot Proposed",C14="Blueprint Funded",C14="Pilot Funded",C14="Won"),U14=""),"WARN: Stage requires reply date",IF(AND(X14="Qualified",U14=""),"WARN: Qualified without reply date",IF(AND(C14="Qualified",X14<>"Qualified"),"WARN: Qualified stage mismatch",IF(AND(X14="Qualified",NOT(OR(C14="Qualified",C14="Blueprint Proposed",C14="Pilot Proposed",C14="Blueprint Funded",C14="Pilot Funded",C14="Won"))),"WARN: Qualified value stage mismatch",IF(AND(Z14>0,NOT(OR(Y14="Blueprint",Y14="Direct Pilot"))),"WARN: Quote without sales path",IF(AND(OR(C14="Blueprint Proposed",C14="Blueprint Funded"),Y14<>"Blueprint"),"WARN: Blueprint stage path mismatch",IF(AND(OR(C14="Pilot Proposed",C14="Pilot Funded"),Y14<>"Direct Pilot"),"WARN: Pilot stage path mismatch",IF(AND(OR(C14="Blueprint Proposed",C14="Pilot Proposed",C14="Blueprint Funded",C14="Pilot Funded",C14="Won"),Z14<=0),"WARN: Offer stage without quote",IF(AND(Z14>0,NOT(OR(C14="Blueprint Proposed",C14="Pilot Proposed",C14="Blueprint Funded",C14="Pilot Funded",C14="Won"))),"WARN: Quote stage mismatch",IF(AND(AA14>0,Z14<=0),"WARN: Funded without quote",IF(AND(OR(C14="Blueprint Funded",C14="Pilot Funded",C14="Won"),AA14<=0),"WARN: Funded stage without amount",IF(AND(AA14>0,NOT(OR(C14="Blueprint Funded",C14="Pilot Funded",C14="Won"))),"WARN: Funded value stage mismatch","OK"))))))))))))))
A15: Hold | B15: Hold | C15: Hold | D15: Lead Response | E15: =IF(G15>=90,"A",IF(G15>=80,"B",IF(G15>=70,"C","D"))) | F15: Upwork:~022080037748505517610 | G15: 75 | H15: Upwork | I15: Agentic AI Customer Support System for Real Estate Business | J15: $200.00 | K15: 20 to 50 | L15: 5 days ago | M15: A real-estate sales agent must answer questions, qualify leads, handle objections, book meetings, and send conversation history to CRM, with chat and possibly voice. | N15: One channel, one qualification flow, and one CRM handoff; defer voice until the chat path is stable. | O15: I saw the real-estate sales-agent brief as a chat-first qualification and booking system with CRM handoff. I would keep the first pilot to one channel, one objection path, and one clean handoff before adding voice. I packaged that exact pilot boundary here: https://dali.agents.ge/for/upwork/lead-response?ref=uw-022080037748505517610 If that boundary matches your brief, reply here in Upwork with your primary intake channel, CRM, and the lead classes that must always wait for a person. I will turn those inputs into the first replay set and pass/fail acceptance test before implementation. | P15: https://dali.agents.ge/for/upwork/lead-response?ref=uw-022080037748505517610 | Q15: https://www.upwork.com/jobs/span-class-highlight-Agentic-span-span-class-highlight-span-Customer-Support-System-for-Real-Estate-Business_~022080037748505517610/?referrer_url_path=/nx/search/jobs/ | R15: High confidence; the $200 budget and requirement for proven sales-agent or voice examples make this a holdout. | T15: Unknown | X15: Not Evaluated | Y15: Hold | AE15: =IFERROR((AA15-AD15)/AA15,"") | AG15: Hold | AH15: Not Checked | AI15: Hold row; not part of the current live-listing audit. | AK15: =IF(AND(U15<>"",S15=""),"WARN: Reply date without sent date",IF(AND(OR(C15="Sent",C15="Replied",C15="Qualified",C15="Blueprint Proposed",C15="Pilot Proposed",C15="Blueprint Funded",C15="Pilot Funded",C15="Won"),S15=""),"WARN: Stage requires sent date",IF(AND(OR(C15="Replied",C15="Qualified",C15="Blueprint Proposed",C15="Pilot Proposed",C15="Blueprint Funded",C15="Pilot Funded",C15="Won"),U15=""),"WARN: Stage requires reply date",IF(AND(X15="Qualified",U15=""),"WARN: Qualified without reply date",IF(AND(C15="Qualified",X15<>"Qualified"),"WARN: Qualified stage mismatch",IF(AND(X15="Qualified",NOT(OR(C15="Qualified",C15="Blueprint Proposed",C15="Pilot Proposed",C15="Blueprint Funded",C15="Pilot Funded",C15="Won"))),"WARN: Qualified value stage mismatch",IF(AND(Z15>0,NOT(OR(Y15="Blueprint",Y15="Direct Pilot"))),"WARN: Quote without sales path",IF(AND(OR(C15="Blueprint Proposed",C15="Blueprint Funded"),Y15<>"Blueprint"),"WARN: Blueprint stage path mismatch",IF(AND(OR(C15="Pilot Proposed",C15="Pilot Funded"),Y15<>"Direct Pilot"),"WARN: Pilot stage path mismatch",IF(AND(OR(C15="Blueprint Proposed",C15="Pilot Proposed",C15="Blueprint Funded",C15="Pilot Funded",C15="Won"),Z15<=0),"WARN: Offer stage without quote",IF(AND(Z15>0,NOT(OR(C15="Blueprint Proposed",C15="Pilot Proposed",C15="Blueprint Funded",C15="Pilot Funded",C15="Won"))),"WARN: Quote stage mismatch",IF(AND(AA15>0,Z15<=0),"WARN: Funded without quote",IF(AND(OR(C15="Blueprint Funded",C15="Pilot Funded",C15="Won"),AA15<=0),"WARN: Funded stage without amount",IF(AND(AA15>0,NOT(OR(C15="Blueprint Funded",C15="Pilot Funded",C15="Won"))),"WARN: Funded value stage mismatch","OK"))))))))))))))
A16: Wave 1 | B16: Landing Link | C16: Not Sent | D16: Client Inbox | E16: =IF(G16>=90,"A",IF(G16>=80,"B",IF(G16>=70,"C","D"))) | F16: FL.ru:5515592 | G16: 95 | H16: FL.ru | I16: Внедрение ИИ-агента для автоматизации переписок с клиентами | J16: по договоренности | K16: 26 | L16: not saved | M16: Агент для переписки в мессенджерах и по email с интеграцией в коробочный Битрикс24. | N16: Один сценарий переписки, один контур Битрикс24, ручное подтверждение и понятные правила доступа. | O16: Нужен ИИ-агент для переписок в мессенджерах и email с интеграцией в коробочный Битрикс24. У нас в Dali Agency уже собрано готовое продуктовое ядро client-inbox: входящее сообщение → утвержденные источники → черновик ответа + история → разрешенные действия → эскалация, если нет опоры. Мы не пишем систему с нуля. Оплачиваемая работа - кастомизация под вас: ваш канал, CRM, базу ответов и действия, которые требуют подтверждения человеком. Первый пилот кастомизации, который я бы зафиксировал: один канал, один workflow: входящее → черновик ответа → ручное подтверждение → запись в Битрикс24. Упакованная граница пилота и как мы это ведем: https://dali.agents.ge/ru/solutions/client-inbox?ref=fl-5515592 Если граница совпадает, ответьте здесь в проекте FL.ru и пришлите один канал, один набор утвержденных источников и действия, которые всегда ждут человека. Я подтвержу fit и пришлю фиксированный milestone пилота (или короткий платный blueprint, если scope еще рыхлый) до начала реализации. | P16: https://dali.agents.ge/ru/solutions/client-inbox?ref=fl-5515592 | Q16: https://www.fl.ru/projects/5515592/vnedrenie-ii-agenta-dlya-avtomatizatsii-perepisok-s-klientami.html | R16: High confidence; 26 ответов, бюджет не указан, privacy, доступы к CRM и approval не описаны. | T16: Unknown | X16: Not Evaluated | Y16: Unassigned | AE16: =IFERROR((AA16-AD16)/AA16,"") | AG16: Batch A | AH16: Open | AI16: Direct page returned 200 with an active response CTA; title and scope matched. | AJ16: 2026-07-30 03:13 +04 | AK16: =IF(AND(U16<>"",S16=""),"WARN: Reply date without sent date",IF(AND(OR(C16="Sent",C16="Replied",C16="Qualified",C16="Blueprint Proposed",C16="Pilot Proposed",C16="Blueprint Funded",C16="Pilot Funded",C16="Won"),S16=""),"WARN: Stage requires sent date",IF(AND(OR(C16="Replied",C16="Qualified",C16="Blueprint Proposed",C16="Pilot Proposed",C16="Blueprint Funded",C16="Pilot Funded",C16="Won"),U16=""),"WARN: Stage requires reply date",IF(AND(X16="Qualified",U16=""),"WARN: Qualified without reply date",IF(AND(C16="Qualified",X16<>"Qualified"),"WARN: Qualified stage mismatch",IF(AND(X16="Qualified",NOT(OR(C16="Qualified",C16="Blueprint Proposed",C16="Pilot Proposed",C16="Blueprint Funded",C16="Pilot Funded",C16="Won"))),"WARN: Qualified value stage mismatch",IF(AND(Z16>0,NOT(OR(Y16="Blueprint",Y16="Direct Pilot"))),"WARN: Quote without sales path",IF(AND(OR(C16="Blueprint Proposed",C16="Blueprint Funded"),Y16<>"Blueprint"),"WARN: Blueprint stage path mismatch",IF(AND(OR(C16="Pilot Proposed",C16="Pilot Funded"),Y16<>"Direct Pilot"),"WARN: Pilot stage path mismatch",IF(AND(OR(C16="Blueprint Proposed",C16="Pilot Proposed",C16="Blueprint Funded",C16="Pilot Funded",C16="Won"),Z16<=0),"WARN: Offer stage without quote",IF(AND(Z16>0,NOT(OR(C16="Blueprint Proposed",C16="Pilot Proposed",C16="Blueprint Funded",C16="Pilot Funded",C16="Won"))),"WARN: Quote stage mismatch",IF(AND(AA16>0,Z16<=0),"WARN: Funded without quote",IF(AND(OR(C16="Blueprint Funded",C16="Pilot Funded",C16="Won"),AA16<=0),"WARN: Funded stage without amount",IF(AND(AA16>0,NOT(OR(C16="Blueprint Funded",C16="Pilot Funded",C16="Won"))),"WARN: Funded value stage mismatch","OK"))))))))))))))
A17: Wave 1 | B17: Landing Link | C17: Not Sent | D17: Client Inbox | E17: =IF(G17>=90,"A",IF(G17>=80,"B",IF(G17>=70,"C","D"))) | F17: Upwork:~022069443845701876220 | G17: 95 | H17: Upwork | I17: AI Automation Engineer: Build a Custom Claude Customer Service Agent | J17: Hourly: $40.00 - $80.00 | K17: 50+ | L17: last month | M17: A production Claude customer-service agent must match the team tone, work with files and internal knowledge, send email, update CRM, run only approved workflows, and escalate sensitive actions. | N17: One customer channel, one approved answer and action policy, one CRM history path, one knowledge or file source set, and human review for sensitive actions. | O17: This is not "just a chatbot": controlled customer responses across approved knowledge, files, email, and CRM, with sensitive actions stopped for review. We already have a production-ready product core for this at Dali Agency (client-inbox core): channel message → approved knowledge → draft reply + case history → permitted actions → escalation when evidence is missing. We are not starting from a blank repo. The paid work is customization under your stack: your channel, CRM, approved answer sources, and the actions that need human confirmation. First customization pilot I would lock: one channel, approved knowledge + files, CRM writeback, stop rules for refunds/account changes/unsupported answers. Packaged boundary + how we run that pilot: https://dali.agents.ge/for/upwork/client-inbox?ref=uw-022069443845701876220 If that matches, reply here in Upwork with one channel, one approved source set, and the actions that must always wait for a person. I will confirm fit and send a fixed pilot milestone (or a short paid blueprint if scope is still loose) before any implementation starts. | P17: https://dali.agents.ge/for/upwork/client-inbox?ref=uw-022069443845701876220 | Q17: https://www.upwork.com/jobs/span-class-highlight-span-span-class-highlight-Automation-span-Engineer-Build-Custom-Claude-Customer-Service-span-class-highlight-Agent-span_~022069443845701876220/?referrer_url_path=/nx/search/jobs/ | R17: High confidence; verified client with rating 5 and over $3k spend, but 50+ proposals and a requirement for production communication and MCP or tool-use proof. | T17: Unknown | X17: Not Evaluated | Y17: Unassigned | AE17: =IFERROR((AA17-AD17)/AA17,"") | AG17: Batch C | AH17: Manual Check | AI17: Anonymous direct page was blocked by a Cloudflare challenge. Verify open status and scope inside Upwork. | AJ17: 2026-07-30 03:14 +04 | AK17: =IF(AND(U17<>"",S17=""),"WARN: Reply date without sent date",IF(AND(OR(C17="Sent",C17="Replied",C17="Qualified",C17="Blueprint Proposed",C17="Pilot Proposed",C17="Blueprint Funded",C17="Pilot Funded",C17="Won"),S17=""),"WARN: Stage requires sent date",IF(AND(OR(C17="Replied",C17="Qualified",C17="Blueprint Proposed",C17="Pilot Proposed",C17="Blueprint Funded",C17="Pilot Funded",C17="Won"),U17=""),"WARN: Stage requires reply date",IF(AND(X17="Qualified",U17=""),"WARN: Qualified without reply date",IF(AND(C17="Qualified",X17<>"Qualified"),"WARN: Qualified stage mismatch",IF(AND(X17="Qualified",NOT(OR(C17="Qualified",C17="Blueprint Proposed",C17="Pilot Proposed",C17="Blueprint Funded",C17="Pilot Funded",C17="Won"))),"WARN: Qualified value stage mismatch",IF(AND(Z17>0,NOT(OR(Y17="Blueprint",Y17="Direct Pilot"))),"WARN: Quote without sales path",IF(AND(OR(C17="Blueprint Proposed",C17="Blueprint Funded"),Y17<>"Blueprint"),"WARN: Blueprint stage path mismatch",IF(AND(OR(C17="Pilot Proposed",C17="Pilot Funded"),Y17<>"Direct Pilot"),"WARN: Pilot stage path mismatch",IF(AND(OR(C17="Blueprint Proposed",C17="Pilot Proposed",C17="Blueprint Funded",C17="Pilot Funded",C17="Won"),Z17<=0),"WARN: Offer stage without quote",IF(AND(Z17>0,NOT(OR(C17="Blueprint Proposed",C17="Pilot Proposed",C17="Blueprint Funded",C17="Pilot Funded",C17="Won"))),"WARN: Quote stage mismatch",IF(AND(AA17>0,Z17<=0),"WARN: Funded without quote",IF(AND(OR(C17="Blueprint Funded",C17="Pilot Funded",C17="Won"),AA17<=0),"WARN: Funded stage without amount",IF(AND(AA17>0,NOT(OR(C17="Blueprint Funded",C17="Pilot Funded",C17="Won"))),"WARN: Funded value stage mismatch","OK"))))))))))))))
A18: Wave 1 | B18: Landing Link | C18: Not Sent | D18: Client Inbox | E18: =IF(G18>=90,"A",IF(G18>=80,"B",IF(G18>=70,"C","D"))) | F18: FL.ru:5514909 | G18: 93 | H18: FL.ru | I18: Интеграция GPT и Битрикс для международной логистики | J18: по договоренности | K18: 45 | L18: not saved | M18: Для логистической компании нужна AI-система на базе Битрикс24 и n8n, но текущий процесс описан слишком широко. | N18: Один клиентский канал, один сценарий ответа или действия, запись результата в Битрикс24 и очередь подтверждения для исключений. | O18: GPT + Битрикс24 + n8n для международной логистики: ответы клиентам по утвержденному контексту и запись результата. У нас в Dali Agency уже собрано готовое продуктовое ядро client-inbox: входящее сообщение → утвержденные источники → черновик ответа + история → разрешенные действия → эскалация, если нет опоры. Мы не пишем систему с нуля. Оплачиваемая работа - кастомизация под вас: ваш канал, CRM, базу ответов и действия, которые требуют подтверждения человеком. Первый пилот кастомизации, который я бы зафиксировал: один клиентский сценарий: входящее обращение → ответ по approved-контексту → запись результата в Битрикс24. Упакованная граница пилота и как мы это ведем: https://dali.agents.ge/ru/solutions/client-inbox?ref=fl-5514909 Если граница совпадает, ответьте здесь в проекте FL.ru и пришлите один канал, один набор утвержденных источников и действия, которые всегда ждут человека. Я подтвержу fit и пришлю фиксированный milestone пилота (или короткий платный blueprint, если scope еще рыхлый) до начала реализации. | P18: https://dali.agents.ge/ru/solutions/client-inbox?ref=fl-5514909 | Q18: https://www.fl.ru/projects/5514909/integratsiya-gpt-i-bitriks-dlya-mejdunarodnoy-logistiki-.html | R18: High confidence; 45 ответов, широкий scope, бюджет и acceptance criteria не определены. | T18: Unknown | X18: Not Evaluated | Y18: Unassigned | AE18: =IFERROR((AA18-AD18)/AA18,"") | AG18: Batch B | AH18: Open | AI18: Direct page is open with 48 responses. Scope is broader than one pilot; pitch only the funded commercial-assistant first phase. | AJ18: 2026-07-30 03:13 +04 | AK18: =IF(AND(U18<>"",S18=""),"WARN: Reply date without sent date",IF(AND(OR(C18="Sent",C18="Replied",C18="Qualified",C18="Blueprint Proposed",C18="Pilot Proposed",C18="Blueprint Funded",C18="Pilot Funded",C18="Won"),S18=""),"WARN: Stage requires sent date",IF(AND(OR(C18="Replied",C18="Qualified",C18="Blueprint Proposed",C18="Pilot Proposed",C18="Blueprint Funded",C18="Pilot Funded",C18="Won"),U18=""),"WARN: Stage requires reply date",IF(AND(X18="Qualified",U18=""),"WARN: Qualified without reply date",IF(AND(C18="Qualified",X18<>"Qualified"),"WARN: Qualified stage mismatch",IF(AND(X18="Qualified",NOT(OR(C18="Qualified",C18="Blueprint Proposed",C18="Pilot Proposed",C18="Blueprint Funded",C18="Pilot Funded",C18="Won"))),"WARN: Qualified value stage mismatch",IF(AND(Z18>0,NOT(OR(Y18="Blueprint",Y18="Direct Pilot"))),"WARN: Quote without sales path",IF(AND(OR(C18="Blueprint Proposed",C18="Blueprint Funded"),Y18<>"Blueprint"),"WARN: Blueprint stage path mismatch",IF(AND(OR(C18="Pilot Proposed",C18="Pilot Funded"),Y18<>"Direct Pilot"),"WARN: Pilot stage path mismatch",IF(AND(OR(C18="Blueprint Proposed",C18="Pilot Proposed",C18="Blueprint Funded",C18="Pilot Funded",C18="Won"),Z18<=0),"WARN: Offer stage without quote",IF(AND(Z18>0,NOT(OR(C18="Blueprint Proposed",C18="Pilot Proposed",C18="Blueprint Funded",C18="Pilot Funded",C18="Won"))),"WARN: Quote stage mismatch",IF(AND(AA18>0,Z18<=0),"WARN: Funded without quote",IF(AND(OR(C18="Blueprint Funded",C18="Pilot Funded",C18="Won"),AA18<=0),"WARN: Funded stage without amount",IF(AND(AA18>0,NOT(OR(C18="Blueprint Funded",C18="Pilot Funded",C18="Won"))),"WARN: Funded value stage mismatch","OK"))))))))))))))
A19: Wave 1 | B19: Landing Link | C19: Not Sent | D19: Client Inbox | E19: =IF(G19>=90,"A",IF(G19>=80,"B",IF(G19>=70,"C","D"))) | F19: FL.ru:5513206 | G19: 92 | H19: FL.ru | I19: AI агент | J19: по договоренности | K19: 17 | L19: not saved | M19: Агент в Битрикс24 должен отслеживать открытые линии, разбирать файлы и работать с клиентскими чатами. | N19: Одна открытая линия, один набор файлов и правил ответа, одна запись истории в Битрикс24 и обязательный human review для чувствительных действий. | O19: AI-агент для открытых линий, чатов и файлов внутри Битрикс24. У нас в Dali Agency уже собрано готовое продуктовое ядро client-inbox: входящее сообщение → утвержденные источники → черновик ответа + история → разрешенные действия → эскалация, если нет опоры. Мы не пишем систему с нуля. Оплачиваемая работа - кастомизация под вас: ваш канал, CRM, базу ответов и действия, которые требуют подтверждения человеком. Первый пилот кастомизации, который я бы зафиксировал: одна линия: прочитать обращение и файл → подготовить ответ → записать историю → передать человеку спорные кейсы. Упакованная граница пилота и как мы это ведем: https://dali.agents.ge/ru/solutions/client-inbox?ref=fl-5513206 Если граница совпадает, ответьте здесь в проекте FL.ru и пришлите один канал, один набор утвержденных источников и действия, которые всегда ждут человека. Я подтвержу fit и пришлю фиксированный milestone пилота (или короткий платный blueprint, если scope еще рыхлый) до начала реализации. | P19: https://dali.agents.ge/ru/solutions/client-inbox?ref=fl-5513206 | Q19: https://www.fl.ru/projects/5513206/ai-agent.html | R19: High confidence; 17 ответов, доступ к чатам и файлам, персональные данные и human review требуют отдельной проверки. | T19: Unknown | X19: Not Evaluated | Y19: Unassigned | AE19: =IFERROR((AA19-AD19)/AA19,"") | AG19: Batch C | AH19: Open | AI19: Direct page returned 200 with an active response CTA; Bitrix24, chat, files, OCR, CRM, and human-escalation scope matched. | AJ19: 2026-07-30 03:14 +04 | AK19: =IF(AND(U19<>"",S19=""),"WARN: Reply date without sent date",IF(AND(OR(C19="Sent",C19="Replied",C19="Qualified",C19="Blueprint Proposed",C19="Pilot Proposed",C19="Blueprint Funded",C19="Pilot Funded",C19="Won"),S19=""),"WARN: Stage requires sent date",IF(AND(OR(C19="Replied",C19="Qualified",C19="Blueprint Proposed",C19="Pilot Proposed",C19="Blueprint Funded",C19="Pilot Funded",C19="Won"),U19=""),"WARN: Stage requires reply date",IF(AND(X19="Qualified",U19=""),"WARN: Qualified without reply date",IF(AND(C19="Qualified",X19<>"Qualified"),"WARN: Qualified stage mismatch",IF(AND(X19="Qualified",NOT(OR(C19="Qualified",C19="Blueprint Proposed",C19="Pilot Proposed",C19="Blueprint Funded",C19="Pilot Funded",C19="Won"))),"WARN: Qualified value stage mismatch",IF(AND(Z19>0,NOT(OR(Y19="Blueprint",Y19="Direct Pilot"))),"WARN: Quote without sales path",IF(AND(OR(C19="Blueprint Proposed",C19="Blueprint Funded"),Y19<>"Blueprint"),"WARN: Blueprint stage path mismatch",IF(AND(OR(C19="Pilot Proposed",C19="Pilot Funded"),Y19<>"Direct Pilot"),"WARN: Pilot stage path mismatch",IF(AND(OR(C19="Blueprint Proposed",C19="Pilot Proposed",C19="Blueprint Funded",C19="Pilot Funded",C19="Won"),Z19<=0),"WARN: Offer stage without quote",IF(AND(Z19>0,NOT(OR(C19="Blueprint Proposed",C19="Pilot Proposed",C19="Blueprint Funded",C19="Pilot Funded",C19="Won"))),"WARN: Quote stage mismatch",IF(AND(AA19>0,Z19<=0),"WARN: Funded without quote",IF(AND(OR(C19="Blueprint Funded",C19="Pilot Funded",C19="Won"),AA19<=0),"WARN: Funded stage without amount",IF(AND(AA19>0,NOT(OR(C19="Blueprint Funded",C19="Pilot Funded",C19="Won"))),"WARN: Funded value stage mismatch","OK"))))))))))))))
A20: Wave 1 | B20: Landing Link | C20: Not Sent | D20: Client Inbox | E20: =IF(G20>=90,"A",IF(G20>=80,"B",IF(G20>=70,"C","D"))) | F20: Upwork:~022081818297985759122 | G20: 70 | H20: Upwork | I20: n8n AI Automation Specialist for Chatbot | J20: Hourly: $19-$40 | K20: 20 to 50 | L20: yesterday | M20: An omnichannel assistant called Sara must use n8n, RAG, and web chat across several customer platforms, but the channels, sources, CRM, and quality criteria are not named. | N20: One customer channel, one approved knowledge set, one CRM or case-history destination, and one escalation queue. | O20: Sara needs an omnichannel assistant with RAG, n8n, and controlled customer replies - not an unsupervised chatbot. We already have a production-ready product core for this at Dali Agency (client-inbox core): channel message → approved knowledge → draft reply + case history → permitted actions → escalation when evidence is missing. We are not starting from a blank repo. The paid work is customization under your stack: your channel, CRM, approved answer sources, and the actions that need human confirmation. First customization pilot I would lock: one customer channel, one approved RAG source set, one case-history destination, and a hard escalation rule. Packaged boundary + how we run that pilot: https://dali.agents.ge/for/upwork/client-inbox?ref=uw-022081818297985759122 If that matches, reply here in Upwork with one channel, one approved source set, and the actions that must always wait for a person. I will confirm fit and send a fixed pilot milestone (or a short paid blueprint if scope is still loose) before any implementation starts. | P20: https://dali.agents.ge/for/upwork/client-inbox?ref=uw-022081818297985759122 | Q20: https://www.upwork.com/jobs/n8n-Automation-Specialist-for-Chatbot_~022081818297985759122/?referrer_url_path=find_work_home | R20: Medium-high confidence; 20-50 proposals, unverified client, and an under-specified brief with no named channels, sources, CRM, or deliverables. | T20: Unknown | X20: Not Evaluated | Y20: Unassigned | AE20: =IFERROR((AA20-AD20)/AA20,"") | AG20: Batch A | AH20: Open | AI20: Full card accessible and scope matched. 20-50 proposals and client viewed yesterday. | AJ20: 2026-07-30 03:16 +04 | AK20: =IF(AND(U20<>"",S20=""),"WARN: Reply date without sent date",IF(AND(OR(C20="Sent",C20="Replied",C20="Qualified",C20="Blueprint Proposed",C20="Pilot Proposed",C20="Blueprint Funded",C20="Pilot Funded",C20="Won"),S20=""),"WARN: Stage requires sent date",IF(AND(OR(C20="Replied",C20="Qualified",C20="Blueprint Proposed",C20="Pilot Proposed",C20="Blueprint Funded",C20="Pilot Funded",C20="Won"),U20=""),"WARN: Stage requires reply date",IF(AND(X20="Qualified",U20=""),"WARN: Qualified without reply date",IF(AND(C20="Qualified",X20<>"Qualified"),"WARN: Qualified stage mismatch",IF(AND(X20="Qualified",NOT(OR(C20="Qualified",C20="Blueprint Proposed",C20="Pilot Proposed",C20="Blueprint Funded",C20="Pilot Funded",C20="Won"))),"WARN: Qualified value stage mismatch",IF(AND(Z20>0,NOT(OR(Y20="Blueprint",Y20="Direct Pilot"))),"WARN: Quote without sales path",IF(AND(OR(C20="Blueprint Proposed",C20="Blueprint Funded"),Y20<>"Blueprint"),"WARN: Blueprint stage path mismatch",IF(AND(OR(C20="Pilot Proposed",C20="Pilot Funded"),Y20<>"Direct Pilot"),"WARN: Pilot stage path mismatch",IF(AND(OR(C20="Blueprint Proposed",C20="Pilot Proposed",C20="Blueprint Funded",C20="Pilot Funded",C20="Won"),Z20<=0),"WARN: Offer stage without quote",IF(AND(Z20>0,NOT(OR(C20="Blueprint Proposed",C20="Pilot Proposed",C20="Blueprint Funded",C20="Pilot Funded",C20="Won"))),"WARN: Quote stage mismatch",IF(AND(AA20>0,Z20<=0),"WARN: Funded without quote",IF(AND(OR(C20="Blueprint Funded",C20="Pilot Funded",C20="Won"),AA20<=0),"WARN: Funded stage without amount",IF(AND(AA20>0,NOT(OR(C20="Blueprint Funded",C20="Pilot Funded",C20="Won"))),"WARN: Funded value stage mismatch","OK"))))))))))))))
A21: Wave 1 | B21: No-Link Diagnostic | C21: Not Sent | D21: Client Inbox | E21: =IF(G21>=90,"A",IF(G21>=80,"B",IF(G21>=70,"C","D"))) | F21: FL.ru:5515230 | G21: 90 | H21: FL.ru | I21: Подключить ИИ-ассистента для переписки и отправки фотографий в чате | J21: по договоренности | K21: 24 | L21: not saved | M21: Ассистент для переписки, фото и видео с клиентами с подключением к Kommo. | N21: Один чат workflow с правилом отправки медиа, логированием в CRM и явным human approval. | O21: Переписка и отправка фото/видео клиентам через Kommo с контролем действий. У нас в Dali Agency уже собрано готовое продуктовое ядро client-inbox: входящее сообщение → утвержденные источники → черновик ответа + история → разрешенные действия → эскалация, если нет опоры. Мы не пишем систему с нуля. Оплачиваемая работа - кастомизация под вас: ваш канал, CRM, базу ответов и действия, которые требуют подтверждения человеком. Первый пилот кастомизации, который я бы зафиксировал: один чат, одно правило отправки медиа, ручное подтверждение перед любым внешним действием. Если граница совпадает, ответьте здесь в проекте FL.ru и пришлите один канал, один набор утвержденных источников и действия, которые всегда ждут человека. Я подтвержу fit и пришлю фиксированный milestone пилота (или короткий платный blueprint, если scope еще рыхлый) до начала реализации. | P21: No link in diagnostic proposal | Q21: https://www.fl.ru/projects/5515230/podklyuchit-ii-asisstenta-dlya-prepiski-i-otpravki-fotografiy-v-chate.html | R21: High confidence; consent, media rights, CRM permissions и human approval не описаны. | T21: Unknown | X21: Not Evaluated | Y21: Unassigned | AE21: =IFERROR((AA21-AD21)/AA21,"") | AG21: Batch B | AH21: Open | AI21: Direct page is open with 25 responses; client-chat, media, Kommo, and handoff scope still matches. | AJ21: 2026-07-30 03:13 +04 | AK21: =IF(AND(U21<>"",S21=""),"WARN: Reply date without sent date",IF(AND(OR(C21="Sent",C21="Replied",C21="Qualified",C21="Blueprint Proposed",C21="Pilot Proposed",C21="Blueprint Funded",C21="Pilot Funded",C21="Won"),S21=""),"WARN: Stage requires sent date",IF(AND(OR(C21="Replied",C21="Qualified",C21="Blueprint Proposed",C21="Pilot Proposed",C21="Blueprint Funded",C21="Pilot Funded",C21="Won"),U21=""),"WARN: Stage requires reply date",IF(AND(X21="Qualified",U21=""),"WARN: Qualified without reply date",IF(AND(C21="Qualified",X21<>"Qualified"),"WARN: Qualified stage mismatch",IF(AND(X21="Qualified",NOT(OR(C21="Qualified",C21="Blueprint Proposed",C21="Pilot Proposed",C21="Blueprint Funded",C21="Pilot Funded",C21="Won"))),"WARN: Qualified value stage mismatch",IF(AND(Z21>0,NOT(OR(Y21="Blueprint",Y21="Direct Pilot"))),"WARN: Quote without sales path",IF(AND(OR(C21="Blueprint Proposed",C21="Blueprint Funded"),Y21<>"Blueprint"),"WARN: Blueprint stage path mismatch",IF(AND(OR(C21="Pilot Proposed",C21="Pilot Funded"),Y21<>"Direct Pilot"),"WARN: Pilot stage path mismatch",IF(AND(OR(C21="Blueprint Proposed",C21="Pilot Proposed",C21="Blueprint Funded",C21="Pilot Funded",C21="Won"),Z21<=0),"WARN: Offer stage without quote",IF(AND(Z21>0,NOT(OR(C21="Blueprint Proposed",C21="Pilot Proposed",C21="Blueprint Funded",C21="Pilot Funded",C21="Won"))),"WARN: Quote stage mismatch",IF(AND(AA21>0,Z21<=0),"WARN: Funded without quote",IF(AND(OR(C21="Blueprint Funded",C21="Pilot Funded",C21="Won"),AA21<=0),"WARN: Funded stage without amount",IF(AND(AA21>0,NOT(OR(C21="Blueprint Funded",C21="Pilot Funded",C21="Won"))),"WARN: Funded value stage mismatch","OK"))))))))))))))
A22: Hold | B22: Hold | C22: Hold | D22: Client Inbox | E22: =IF(G22>=90,"A",IF(G22>=80,"B",IF(G22>=70,"C","D"))) | F22: Upwork:~022075920337694781992 | G22: 60 | H22: Upwork | I22: AI Automation Expert | J22: $1,500.00 | K22: 50+ | L22: 3 weeks ago | M22: The client wants a complete e-commerce support agent, but the brief does not specify channels, knowledge, integrations, escalation, languages, or quality criteria. | N22: One support channel, one approved knowledge and store-context set, one case-history destination, and human handoff. | O22: A complete e-commerce support agent is too broad to validate in one step. I would first replay one support channel against an approved store-context set, log every outcome, and route any unsupported or sensitive action to a person. I packaged that exact pilot boundary here: https://dali.agents.ge/for/upwork/client-inbox?ref=uw-022075920337694781992 If that boundary matches your brief, reply here in Upwork with your primary customer channel, CRM or case history, and one representative thread. I will turn those inputs into the first replay set and pass/fail acceptance test before implementation. | P22: https://dali.agents.ge/for/upwork/client-inbox?ref=uw-022075920337694781992 | Q22: https://www.upwork.com/jobs/span-class-highlight-span-span-class-highlight-Automation-span-Expert_~022075920337694781992/?referrer_url_path=/nx/search/jobs/ | R22: Medium confidence; $1,500, verified payment, rating 5, and over $2k spend are positive, but the one-line brief and 50+ proposals make scope unknown. | T22: Unknown | X22: Not Evaluated | Y22: Hold | AE22: =IFERROR((AA22-AD22)/AA22,"") | AG22: Hold | AH22: Not Checked | AI22: Hold row; not part of the current live-listing audit. | AK22: =IF(AND(U22<>"",S22=""),"WARN: Reply date without sent date",IF(AND(OR(C22="Sent",C22="Replied",C22="Qualified",C22="Blueprint Proposed",C22="Pilot Proposed",C22="Blueprint Funded",C22="Pilot Funded",C22="Won"),S22=""),"WARN: Stage requires sent date",IF(AND(OR(C22="Replied",C22="Qualified",C22="Blueprint Proposed",C22="Pilot Proposed",C22="Blueprint Funded",C22="Pilot Funded",C22="Won"),U22=""),"WARN: Stage requires reply date",IF(AND(X22="Qualified",U22=""),"WARN: Qualified without reply date",IF(AND(C22="Qualified",X22<>"Qualified"),"WARN: Qualified stage mismatch",IF(AND(X22="Qualified",NOT(OR(C22="Qualified",C22="Blueprint Proposed",C22="Pilot Proposed",C22="Blueprint Funded",C22="Pilot Funded",C22="Won"))),"WARN: Qualified value stage mismatch",IF(AND(Z22>0,NOT(OR(Y22="Blueprint",Y22="Direct Pilot"))),"WARN: Quote without sales path",IF(AND(OR(C22="Blueprint Proposed",C22="Blueprint Funded"),Y22<>"Blueprint"),"WARN: Blueprint stage path mismatch",IF(AND(OR(C22="Pilot Proposed",C22="Pilot Funded"),Y22<>"Direct Pilot"),"WARN: Pilot stage path mismatch",IF(AND(OR(C22="Blueprint Proposed",C22="Pilot Proposed",C22="Blueprint Funded",C22="Pilot Funded",C22="Won"),Z22<=0),"WARN: Offer stage without quote",IF(AND(Z22>0,NOT(OR(C22="Blueprint Proposed",C22="Pilot Proposed",C22="Blueprint Funded",C22="Pilot Funded",C22="Won"))),"WARN: Quote stage mismatch",IF(AND(AA22>0,Z22<=0),"WARN: Funded without quote",IF(AND(OR(C22="Blueprint Funded",C22="Pilot Funded",C22="Won"),AA22<=0),"WARN: Funded stage without amount",IF(AND(AA22>0,NOT(OR(C22="Blueprint Funded",C22="Pilot Funded",C22="Won"))),"WARN: Funded value stage mismatch","OK"))))))))))))))
A23: Wave 1 | B23: Landing Link | C23: Not Sent | D23: Operations & Documents | E23: =IF(G23>=90,"A",IF(G23>=80,"B",IF(G23>=70,"C","D"))) | F23: Upwork:~022073883528374083136 | G23: 90 | H23: Upwork | I23: AI Automation Engineer Build AI Transaction Coordinator for Brivity CRM Claude + Browser Automation | J23: Hourly: $25.00 - $75.00 | K23: 50+ | L23: 3 weeks ago | M23: Gmail and document inputs must be converted into Brivity deals, uploads, checklist updates, and notifications through UI automation. | N23: One email thread to one deal, document upload, checklist update, notification, and a fallback when the UI changes. | O23: Transaction coordination from Gmail into Brivity with documents, checklists, and UI-change fallbacks is a classic ops pipeline. We already have a production-ready product core for this at Dali Agency (operations-docs core): input → extract/OCR → validate against schema → write to destination → exception queue with audit trail. We are not starting from a blank repo. The paid work is customization under your stack: your input type, required fields, destination system, and exception owner. First customization pilot I would lock: one deal path: Gmail → Brivity record, document upload, checklist update, exception when UI changes. Packaged boundary + how we run that pilot: https://dali.agents.ge/for/upwork/operations-docs?ref=uw-022073883528374083136 If that matches, reply here in Upwork with one representative input, required output fields, target system, and who owns exceptions. I will confirm fit and send a fixed pilot milestone (or a short paid blueprint if scope is still loose) before any implementation starts. | P23: https://dali.agents.ge/for/upwork/operations-docs?ref=uw-022073883528374083136 | Q23: https://www.upwork.com/jobs/span-class-highlight-span-span-class-highlight-Automation-span-Engineer-Build-span-class-highlight-span-Transaction-Coordinator-for-Brivity-CRM-Claude-Browser-span-class-highlight-Automation-span_~022073883528374083136/?referrer_url_path=/nx/search/jobs/ | R23: High confidence; browser automation is fragile and the listing has 50+ proposals. | T23: Unknown | X23: Not Evaluated | Y23: Unassigned | AE23: =IFERROR((AA23-AD23)/AA23,"") | AG23: Batch C | AH23: Manual Check | AI23: Anonymous direct page was blocked by a Cloudflare challenge. Verify open status and scope inside Upwork. | AJ23: 2026-07-30 03:14 +04 | AK23: =IF(AND(U23<>"",S23=""),"WARN: Reply date without sent date",IF(AND(OR(C23="Sent",C23="Replied",C23="Qualified",C23="Blueprint Proposed",C23="Pilot Proposed",C23="Blueprint Funded",C23="Pilot Funded",C23="Won"),S23=""),"WARN: Stage requires sent date",IF(AND(OR(C23="Replied",C23="Qualified",C23="Blueprint Proposed",C23="Pilot Proposed",C23="Blueprint Funded",C23="Pilot Funded",C23="Won"),U23=""),"WARN: Stage requires reply date",IF(AND(X23="Qualified",U23=""),"WARN: Qualified without reply date",IF(AND(C23="Qualified",X23<>"Qualified"),"WARN: Qualified stage mismatch",IF(AND(X23="Qualified",NOT(OR(C23="Qualified",C23="Blueprint Proposed",C23="Pilot Proposed",C23="Blueprint Funded",C23="Pilot Funded",C23="Won"))),"WARN: Qualified value stage mismatch",IF(AND(Z23>0,NOT(OR(Y23="Blueprint",Y23="Direct Pilot"))),"WARN: Quote without sales path",IF(AND(OR(C23="Blueprint Proposed",C23="Blueprint Funded"),Y23<>"Blueprint"),"WARN: Blueprint stage path mismatch",IF(AND(OR(C23="Pilot Proposed",C23="Pilot Funded"),Y23<>"Direct Pilot"),"WARN: Pilot stage path mismatch",IF(AND(OR(C23="Blueprint Proposed",C23="Pilot Proposed",C23="Blueprint Funded",C23="Pilot Funded",C23="Won"),Z23<=0),"WARN: Offer stage without quote",IF(AND(Z23>0,NOT(OR(C23="Blueprint Proposed",C23="Pilot Proposed",C23="Blueprint Funded",C23="Pilot Funded",C23="Won"))),"WARN: Quote stage mismatch",IF(AND(AA23>0,Z23<=0),"WARN: Funded without quote",IF(AND(OR(C23="Blueprint Funded",C23="Pilot Funded",C23="Won"),AA23<=0),"WARN: Funded stage without amount",IF(AND(AA23>0,NOT(OR(C23="Blueprint Funded",C23="Pilot Funded",C23="Won"))),"WARN: Funded value stage mismatch","OK"))))))))))))))
A24: Wave 1 | B24: Landing Link | C24: Not Sent | D24: Operations & Documents | E24: =IF(G24>=90,"A",IF(G24>=80,"B",IF(G24>=70,"C","D"))) | F24: Upwork:~022079631969043129867 | G24: 90 | H24: Upwork | I24: AI Workflow Automation Developer for Order Processing and Operations | J24: $300.00 | K24: 50+ | L24: last week | M24: Fragmented wholesale order intake needs reliable checks, duplicate prevention, exception handling, and a clean system update. | N24: One intake source, one schema, one destination, one approval rule, and one exception queue. | O24: Order processing from email/PDF/sheet into ERP/CRM is high-value only if every write is validated and deduped. We already have a production-ready product core for this at Dali Agency (operations-docs core): input → extract/OCR → validate against schema → write to destination → exception queue with audit trail. We are not starting from a blank repo. The paid work is customization under your stack: your input type, required fields, destination system, and exception owner. First customization pilot I would lock: one auditable path from email/PDF/sheet → validated ERP/CRM draft, human exception queue, dedupe rules. Packaged boundary + how we run that pilot: https://dali.agents.ge/for/upwork/operations-docs?ref=uw-022079631969043129867 If that matches, reply here in Upwork with one representative input, required output fields, target system, and who owns exceptions. I will confirm fit and send a fixed pilot milestone (or a short paid blueprint if scope is still loose) before any implementation starts. | P24: https://dali.agents.ge/for/upwork/operations-docs?ref=uw-022079631969043129867 | Q24: https://www.upwork.com/jobs/span-class-highlight-span-Workflow-span-class-highlight-Automation-span-Developer-for-Order-Processing-and-Operations_~022079631969043129867/?referrer_url_path=/nx/search/jobs/ | R24: High confidence; the $300 budget is too small for the full order-processing scope. | T24: Unknown | X24: Not Evaluated | Y24: Unassigned | AE24: =IFERROR((AA24-AD24)/AA24,"") | AG24: Batch C | AH24: Manual Check | AI24: Anonymous direct page was blocked by a Cloudflare challenge. Verify open status and scope inside Upwork. | AJ24: 2026-07-30 03:14 +04 | AK24: =IF(AND(U24<>"",S24=""),"WARN: Reply date without sent date",IF(AND(OR(C24="Sent",C24="Replied",C24="Qualified",C24="Blueprint Proposed",C24="Pilot Proposed",C24="Blueprint Funded",C24="Pilot Funded",C24="Won"),S24=""),"WARN: Stage requires sent date",IF(AND(OR(C24="Replied",C24="Qualified",C24="Blueprint Proposed",C24="Pilot Proposed",C24="Blueprint Funded",C24="Pilot Funded",C24="Won"),U24=""),"WARN: Stage requires reply date",IF(AND(X24="Qualified",U24=""),"WARN: Qualified without reply date",IF(AND(C24="Qualified",X24<>"Qualified"),"WARN: Qualified stage mismatch",IF(AND(X24="Qualified",NOT(OR(C24="Qualified",C24="Blueprint Proposed",C24="Pilot Proposed",C24="Blueprint Funded",C24="Pilot Funded",C24="Won"))),"WARN: Qualified value stage mismatch",IF(AND(Z24>0,NOT(OR(Y24="Blueprint",Y24="Direct Pilot"))),"WARN: Quote without sales path",IF(AND(OR(C24="Blueprint Proposed",C24="Blueprint Funded"),Y24<>"Blueprint"),"WARN: Blueprint stage path mismatch",IF(AND(OR(C24="Pilot Proposed",C24="Pilot Funded"),Y24<>"Direct Pilot"),"WARN: Pilot stage path mismatch",IF(AND(OR(C24="Blueprint Proposed",C24="Pilot Proposed",C24="Blueprint Funded",C24="Pilot Funded",C24="Won"),Z24<=0),"WARN: Offer stage without quote",IF(AND(Z24>0,NOT(OR(C24="Blueprint Proposed",C24="Pilot Proposed",C24="Blueprint Funded",C24="Pilot Funded",C24="Won"))),"WARN: Quote stage mismatch",IF(AND(AA24>0,Z24<=0),"WARN: Funded without quote",IF(AND(OR(C24="Blueprint Funded",C24="Pilot Funded",C24="Won"),AA24<=0),"WARN: Funded stage without amount",IF(AND(AA24>0,NOT(OR(C24="Blueprint Funded",C24="Pilot Funded",C24="Won"))),"WARN: Funded value stage mismatch","OK"))))))))))))))
A25: Wave 1 | B25: Landing Link | C25: Not Sent | D25: Operations & Documents | E25: =IF(G25>=90,"A",IF(G25>=80,"B",IF(G25>=70,"C","D"))) | F25: Upwork:~022081598123554232311 | G25: 85 | H25: Upwork | I25: AI-Powered Property Management & Tenant Operations Automation | J25: Hourly: $15.00 - $25.00 | K25: 20 to 50 | L25: yesterday | M25: Tenant WhatsApp messages and screenshots must connect to Buildium, QuickBooks, repairs, exceptions, and an audit trail. | N25: One payment or maintenance workflow with OCR, one system check, one sync, and one exception queue. | O25: Tenant WhatsApp messages and screenshots into Buildium/QuickBooks with repairs, exceptions, and audit is the right ops pattern. We already have a production-ready product core for this at Dali Agency (operations-docs core): input → extract/OCR → validate against schema → write to destination → exception queue with audit trail. We are not starting from a blank repo. The paid work is customization under your stack: your input type, required fields, destination system, and exception owner. First customization pilot I would lock: one tenant workflow: WhatsApp/screenshot → OCR → Buildium check → QuickBooks sync → exception queue. Packaged boundary + how we run that pilot: https://dali.agents.ge/for/upwork/operations-docs?ref=uw-022081598123554232311 If that matches, reply here in Upwork with one representative input, required output fields, target system, and who owns exceptions. I will confirm fit and send a fixed pilot milestone (or a short paid blueprint if scope is still loose) before any implementation starts. | P25: https://dali.agents.ge/for/upwork/operations-docs?ref=uw-022081598123554232311 | Q25: https://www.upwork.com/jobs/span-class-highlight-span-Powered-Property-Management-amp-Tenant-Operations-span-class-highlight-Automation-span_~022081598123554232311/?referrer_url_path=/nx/search/jobs/ | R25: High confidence; multi-system access and OCR quality are material risks. | T25: Unknown | X25: Not Evaluated | Y25: Unassigned | AE25: =IFERROR((AA25-AD25)/AA25,"") | AG25: Batch B | AH25: Manual Check | AI25: Anonymous direct page was blocked by a Cloudflare challenge. Verify open status and scope inside Upwork. | AJ25: 2026-07-30 03:13 +04 | AK25: =IF(AND(U25<>"",S25=""),"WARN: Reply date without sent date",IF(AND(OR(C25="Sent",C25="Replied",C25="Qualified",C25="Blueprint Proposed",C25="Pilot Proposed",C25="Blueprint Funded",C25="Pilot Funded",C25="Won"),S25=""),"WARN: Stage requires sent date",IF(AND(OR(C25="Replied",C25="Qualified",C25="Blueprint Proposed",C25="Pilot Proposed",C25="Blueprint Funded",C25="Pilot Funded",C25="Won"),U25=""),"WARN: Stage requires reply date",IF(AND(X25="Qualified",U25=""),"WARN: Qualified without reply date",IF(AND(C25="Qualified",X25<>"Qualified"),"WARN: Qualified stage mismatch",IF(AND(X25="Qualified",NOT(OR(C25="Qualified",C25="Blueprint Proposed",C25="Pilot Proposed",C25="Blueprint Funded",C25="Pilot Funded",C25="Won"))),"WARN: Qualified value stage mismatch",IF(AND(Z25>0,NOT(OR(Y25="Blueprint",Y25="Direct Pilot"))),"WARN: Quote without sales path",IF(AND(OR(C25="Blueprint Proposed",C25="Blueprint Funded"),Y25<>"Blueprint"),"WARN: Blueprint stage path mismatch",IF(AND(OR(C25="Pilot Proposed",C25="Pilot Funded"),Y25<>"Direct Pilot"),"WARN: Pilot stage path mismatch",IF(AND(OR(C25="Blueprint Proposed",C25="Pilot Proposed",C25="Blueprint Funded",C25="Pilot Funded",C25="Won"),Z25<=0),"WARN: Offer stage without quote",IF(AND(Z25>0,NOT(OR(C25="Blueprint Proposed",C25="Pilot Proposed",C25="Blueprint Funded",C25="Pilot Funded",C25="Won"))),"WARN: Quote stage mismatch",IF(AND(AA25>0,Z25<=0),"WARN: Funded without quote",IF(AND(OR(C25="Blueprint Funded",C25="Pilot Funded",C25="Won"),AA25<=0),"WARN: Funded stage without amount",IF(AND(AA25>0,NOT(OR(C25="Blueprint Funded",C25="Pilot Funded",C25="Won"))),"WARN: Funded value stage mismatch","OK"))))))))))))))
A26: Wave 1 | B26: Landing Link | C26: Not Sent | D26: Operations & Documents | E26: =IF(G26>=90,"A",IF(G26>=80,"B",IF(G26>=70,"C","D"))) | F26: Upwork:~022081965076177154541 | G26: 85 | H26: Upwork | I26: Build AI-Powered Zapier Workflow for Automatic Mail Processing (Google Drive + Claude + Discord) | J26: Hourly | K26: 50+ | L26: 12 hours ago | M26: Scanned mail must be OCRed, classified, renamed, filed in Drive, and announced in Discord without manual sorting. | N26: One mailbox, one extraction and naming schema, one Drive destination, and one notification path. | O26: You need scanned mail OCRed, classified, renamed, filed in Drive, and announced in Discord without manual sorting. We already have a production-ready product core for this at Dali Agency (operations-docs core): input → extract/OCR → validate against schema → write to destination → exception queue with audit trail. We are not starting from a blank repo. The paid work is customization under your stack: your input type, required fields, destination system, and exception owner. First customization pilot I would lock: one mailbox → OCR/classify/rename → one Drive folder → one Discord notify path. Packaged boundary + how we run that pilot: https://dali.agents.ge/for/upwork/operations-docs?ref=uw-022081965076177154541 If that matches, reply here in Upwork with one representative input, required output fields, target system, and who owns exceptions. I will confirm fit and send a fixed pilot milestone (or a short paid blueprint if scope is still loose) before any implementation starts. | P26: https://dali.agents.ge/for/upwork/operations-docs?ref=uw-022081965076177154541 | Q26: https://www.upwork.com/jobs/Build-Powered-Zapier-Workflow-for-Automatic-Mail-Processing-Google-Drive-Claude-Discord_~022081965076177154541/?referrer_url_path=find_work_home | R26: High confidence; document-type expansion can quickly enlarge the scope. | T26: Unknown | X26: Not Evaluated | Y26: Unassigned | AE26: =IFERROR((AA26-AD26)/AA26,"") | AG26: Batch A | AH26: Open | AI26: Full card accessible and scope matched. 50+ proposals; client viewed two days ago. | AJ26: 2026-07-30 03:16 +04 | AK26: =IF(AND(U26<>"",S26=""),"WARN: Reply date without sent date",IF(AND(OR(C26="Sent",C26="Replied",C26="Qualified",C26="Blueprint Proposed",C26="Pilot Proposed",C26="Blueprint Funded",C26="Pilot Funded",C26="Won"),S26=""),"WARN: Stage requires sent date",IF(AND(OR(C26="Replied",C26="Qualified",C26="Blueprint Proposed",C26="Pilot Proposed",C26="Blueprint Funded",C26="Pilot Funded",C26="Won"),U26=""),"WARN: Stage requires reply date",IF(AND(X26="Qualified",U26=""),"WARN: Qualified without reply date",IF(AND(C26="Qualified",X26<>"Qualified"),"WARN: Qualified stage mismatch",IF(AND(X26="Qualified",NOT(OR(C26="Qualified",C26="Blueprint Proposed",C26="Pilot Proposed",C26="Blueprint Funded",C26="Pilot Funded",C26="Won"))),"WARN: Qualified value stage mismatch",IF(AND(Z26>0,NOT(OR(Y26="Blueprint",Y26="Direct Pilot"))),"WARN: Quote without sales path",IF(AND(OR(C26="Blueprint Proposed",C26="Blueprint Funded"),Y26<>"Blueprint"),"WARN: Blueprint stage path mismatch",IF(AND(OR(C26="Pilot Proposed",C26="Pilot Funded"),Y26<>"Direct Pilot"),"WARN: Pilot stage path mismatch",IF(AND(OR(C26="Blueprint Proposed",C26="Pilot Proposed",C26="Blueprint Funded",C26="Pilot Funded",C26="Won"),Z26<=0),"WARN: Offer stage without quote",IF(AND(Z26>0,NOT(OR(C26="Blueprint Proposed",C26="Pilot Proposed",C26="Blueprint Funded",C26="Pilot Funded",C26="Won"))),"WARN: Quote stage mismatch",IF(AND(AA26>0,Z26<=0),"WARN: Funded without quote",IF(AND(OR(C26="Blueprint Funded",C26="Pilot Funded",C26="Won"),AA26<=0),"WARN: Funded stage without amount",IF(AND(AA26>0,NOT(OR(C26="Blueprint Funded",C26="Pilot Funded",C26="Won"))),"WARN: Funded value stage mismatch","OK"))))))))))))))
A27: Wave 1 | B27: Landing Link | C27: Not Sent | D27: Operations & Documents | E27: =IF(G27>=90,"A",IF(G27>=80,"B",IF(G27>=70,"C","D"))) | F27: Upwork:~022082121535485723389 | G27: 85 | H27: Upwork | I27: AI Agent Developer for Commodity Data | J27: Hourly: $25-$45 | K27: 20 to 50 | L27: 2 hours ago | M27: The first of three agents must research commodity data only from approved sources and export structured results to Excel and PDF before later validation and reporting stages. | N27: One approved source set, one extraction schema, one structured Excel and PDF output, one validation rule set, and an exception record for unsupported data. | O27: Your first agent should research commodity data only from approved sources and export structured Excel/PDF before later validation stages. We already have a production-ready product core for this at Dali Agency (operations-docs core): input → extract/OCR → validate against schema → write to destination → exception queue with audit trail. We are not starting from a blank repo. The paid work is customization under your stack: your input type, required fields, destination system, and exception owner. First customization pilot I would lock: one approved source set, one extraction schema, one Excel+PDF package, visible exceptions for unsupported data. Packaged boundary + how we run that pilot: https://dali.agents.ge/for/upwork/operations-docs?ref=uw-022082121535485723389 If that matches, reply here in Upwork with one representative input, required output fields, target system, and who owns exceptions. I will confirm fit and send a fixed pilot milestone (or a short paid blueprint if scope is still loose) before any implementation starts. | P27: https://dali.agents.ge/for/upwork/operations-docs?ref=uw-022082121535485723389 | Q27: https://www.upwork.com/jobs/Agent-Developer-for-Commodity-Data_~022082121535485723389/?referrer_url_path=find_work_home | R27: High confidence; 20-50 proposals and an unverified client, with source rules, export quality, and proof of n8n or RAG work still to clarify. | T27: Unknown | X27: Not Evaluated | Y27: Unassigned | AE27: =IFERROR((AA27-AD27)/AA27,"") | AG27: Batch A | AH27: Open | AI27: Full card accessible and scope matched. Competition increased to 50+ proposals with three interviews. | AJ27: 2026-07-30 03:16 +04 | AK27: =IF(AND(U27<>"",S27=""),"WARN: Reply date without sent date",IF(AND(OR(C27="Sent",C27="Replied",C27="Qualified",C27="Blueprint Proposed",C27="Pilot Proposed",C27="Blueprint Funded",C27="Pilot Funded",C27="Won"),S27=""),"WARN: Stage requires sent date",IF(AND(OR(C27="Replied",C27="Qualified",C27="Blueprint Proposed",C27="Pilot Proposed",C27="Blueprint Funded",C27="Pilot Funded",C27="Won"),U27=""),"WARN: Stage requires reply date",IF(AND(X27="Qualified",U27=""),"WARN: Qualified without reply date",IF(AND(C27="Qualified",X27<>"Qualified"),"WARN: Qualified stage mismatch",IF(AND(X27="Qualified",NOT(OR(C27="Qualified",C27="Blueprint Proposed",C27="Pilot Proposed",C27="Blueprint Funded",C27="Pilot Funded",C27="Won"))),"WARN: Qualified value stage mismatch",IF(AND(Z27>0,NOT(OR(Y27="Blueprint",Y27="Direct Pilot"))),"WARN: Quote without sales path",IF(AND(OR(C27="Blueprint Proposed",C27="Blueprint Funded"),Y27<>"Blueprint"),"WARN: Blueprint stage path mismatch",IF(AND(OR(C27="Pilot Proposed",C27="Pilot Funded"),Y27<>"Direct Pilot"),"WARN: Pilot stage path mismatch",IF(AND(OR(C27="Blueprint Proposed",C27="Pilot Proposed",C27="Blueprint Funded",C27="Pilot Funded",C27="Won"),Z27<=0),"WARN: Offer stage without quote",IF(AND(Z27>0,NOT(OR(C27="Blueprint Proposed",C27="Pilot Proposed",C27="Blueprint Funded",C27="Pilot Funded",C27="Won"))),"WARN: Quote stage mismatch",IF(AND(AA27>0,Z27<=0),"WARN: Funded without quote",IF(AND(OR(C27="Blueprint Funded",C27="Pilot Funded",C27="Won"),AA27<=0),"WARN: Funded stage without amount",IF(AND(AA27>0,NOT(OR(C27="Blueprint Funded",C27="Pilot Funded",C27="Won"))),"WARN: Funded value stage mismatch","OK"))))))))))))))
A28: Wave 1 | B28: No-Link Diagnostic | C28: Not Sent | D28: Operations & Documents | E28: =IF(G28>=90,"A",IF(G28>=80,"B",IF(G28>=70,"C","D"))) | F28: FL.ru:5514469 | G28: 88 | H28: FL.ru | I28: Помощь в настройке Claude | J28: по договоренности | K28: 27 | L28: not saved | M28: Нужно автоматически создавать коммерческие предложения и расчеты по шаблонам и заданным параметрам. | N28: Один шаблон коммерческого предложения, одна схема входных параметров, проверка расчетов, один выходной файл и подтверждение перед отправкой. | O28: Автосоздание коммерческих предложений и расчетов по шаблонам и параметрам (Claude). У нас в Dali Agency уже собрано готовое продуктовое ядро operations-docs: вход → извлечение/OCR → проверка схемы → запись в систему → очередь исключений с логом. Мы не пишем систему с нуля. Оплачиваемая работа - кастомизация под вас: тип входа, обязательные поля, целевую систему и владельца исключений. Первый пилот кастомизации, который я бы зафиксировал: один шаблон КП: входные параметры → проверка полей и формул → предпросмотр → подтверждение человеком. Если граница совпадает, ответьте здесь в проекте FL.ru и пришлите один типичный вход, нужные поля, целевую систему и кто проверяет исключения. Я подтвержу fit и пришлю фиксированный milestone пилота (или короткий платный blueprint, если scope еще рыхлый) до начала реализации. | P28: No link in diagnostic proposal | Q28: https://www.fl.ru/projects/5514469/pomosch-v-nastroyke-claude.html | R28: High confidence; 27 ответов, бюджет и критерии корректности расчетов не определены. | T28: Unknown | X28: Not Evaluated | Y28: Unassigned | AE28: =IFERROR((AA28-AD28)/AA28,"") | AG28: Batch B | AH28: Open | AI28: Direct page is open; commercial-proposal and template-calculation scope still matches. Keep the planned diagnostic restrained. | AJ28: 2026-07-30 03:13 +04 | AK28: =IF(AND(U28<>"",S28=""),"WARN: Reply date without sent date",IF(AND(OR(C28="Sent",C28="Replied",C28="Qualified",C28="Blueprint Proposed",C28="Pilot Proposed",C28="Blueprint Funded",C28="Pilot Funded",C28="Won"),S28=""),"WARN: Stage requires sent date",IF(AND(OR(C28="Replied",C28="Qualified",C28="Blueprint Proposed",C28="Pilot Proposed",C28="Blueprint Funded",C28="Pilot Funded",C28="Won"),U28=""),"WARN: Stage requires reply date",IF(AND(X28="Qualified",U28=""),"WARN: Qualified without reply date",IF(AND(C28="Qualified",X28<>"Qualified"),"WARN: Qualified stage mismatch",IF(AND(X28="Qualified",NOT(OR(C28="Qualified",C28="Blueprint Proposed",C28="Pilot Proposed",C28="Blueprint Funded",C28="Pilot Funded",C28="Won"))),"WARN: Qualified value stage mismatch",IF(AND(Z28>0,NOT(OR(Y28="Blueprint",Y28="Direct Pilot"))),"WARN: Quote without sales path",IF(AND(OR(C28="Blueprint Proposed",C28="Blueprint Funded"),Y28<>"Blueprint"),"WARN: Blueprint stage path mismatch",IF(AND(OR(C28="Pilot Proposed",C28="Pilot Funded"),Y28<>"Direct Pilot"),"WARN: Pilot stage path mismatch",IF(AND(OR(C28="Blueprint Proposed",C28="Pilot Proposed",C28="Blueprint Funded",C28="Pilot Funded",C28="Won"),Z28<=0),"WARN: Offer stage without quote",IF(AND(Z28>0,NOT(OR(C28="Blueprint Proposed",C28="Pilot Proposed",C28="Blueprint Funded",C28="Pilot Funded",C28="Won"))),"WARN: Quote stage mismatch",IF(AND(AA28>0,Z28<=0),"WARN: Funded without quote",IF(AND(OR(C28="Blueprint Funded",C28="Pilot Funded",C28="Won"),AA28<=0),"WARN: Funded stage without amount",IF(AND(AA28>0,NOT(OR(C28="Blueprint Funded",C28="Pilot Funded",C28="Won"))),"WARN: Funded value stage mismatch","OK"))))))))))))))
A29: Hold | B29: Hold | C29: Hold | D29: Operations & Documents | E29: =IF(G29>=90,"A",IF(G29>=80,"B",IF(G29>=70,"C","D"))) | F29: Upwork:~022081838181027419548 | G29: 85 | H29: Upwork | I29: n8n Automation Developer for Commercial Restoration | J29: Hourly: $5-$35 | K29: 50+ | L29: 21 hours ago | M29: Open-source incident signals need ingestion, dedupe, field extraction, scoring, storage, and alerting without overwhelming operators. | N29: One source class, one scoring rule, one store, and one notification route. | O29: I would keep the pilot to one event stream first: ingest, dedupe, score, store, alert. That proves signal quality before adding more sources. I packaged that exact pilot boundary here: https://dali.agents.ge/for/upwork/operations-docs?ref=uw-022081838181027419548 If that boundary matches your brief, reply here in Upwork with one representative input, the required output fields, the target system, and the exception owner. I will turn those inputs into the first replay set and pass/fail acceptance test before implementation. | P29: https://dali.agents.ge/for/upwork/operations-docs?ref=uw-022081838181027419548 | Q29: https://www.upwork.com/jobs/n8n-Automation-Developer-for-Commercial-Restoration_~022081838181027419548/?referrer_url_path=find_work_home | R29: High confidence; source quality and false-positive rates can undermine the workflow. | T29: Unknown | X29: Not Evaluated | Y29: Hold | AE29: =IFERROR((AA29-AD29)/AA29,"") | AG29: Hold | AH29: Not Checked | AI29: Hold row; not part of the current live-listing audit. | AK29: =IF(AND(U29<>"",S29=""),"WARN: Reply date without sent date",IF(AND(OR(C29="Sent",C29="Replied",C29="Qualified",C29="Blueprint Proposed",C29="Pilot Proposed",C29="Blueprint Funded",C29="Pilot Funded",C29="Won"),S29=""),"WARN: Stage requires sent date",IF(AND(OR(C29="Replied",C29="Qualified",C29="Blueprint Proposed",C29="Pilot Proposed",C29="Blueprint Funded",C29="Pilot Funded",C29="Won"),U29=""),"WARN: Stage requires reply date",IF(AND(X29="Qualified",U29=""),"WARN: Qualified without reply date",IF(AND(C29="Qualified",X29<>"Qualified"),"WARN: Qualified stage mismatch",IF(AND(X29="Qualified",NOT(OR(C29="Qualified",C29="Blueprint Proposed",C29="Pilot Proposed",C29="Blueprint Funded",C29="Pilot Funded",C29="Won"))),"WARN: Qualified value stage mismatch",IF(AND(Z29>0,NOT(OR(Y29="Blueprint",Y29="Direct Pilot"))),"WARN: Quote without sales path",IF(AND(OR(C29="Blueprint Proposed",C29="Blueprint Funded"),Y29<>"Blueprint"),"WARN: Blueprint stage path mismatch",IF(AND(OR(C29="Pilot Proposed",C29="Pilot Funded"),Y29<>"Direct Pilot"),"WARN: Pilot stage path mismatch",IF(AND(OR(C29="Blueprint Proposed",C29="Pilot Proposed",C29="Blueprint Funded",C29="Pilot Funded",C29="Won"),Z29<=0),"WARN: Offer stage without quote",IF(AND(Z29>0,NOT(OR(C29="Blueprint Proposed",C29="Pilot Proposed",C29="Blueprint Funded",C29="Pilot Funded",C29="Won"))),"WARN: Quote stage mismatch",IF(AND(AA29>0,Z29<=0),"WARN: Funded without quote",IF(AND(OR(C29="Blueprint Funded",C29="Pilot Funded",C29="Won"),AA29<=0),"WARN: Funded stage without amount",IF(AND(AA29>0,NOT(OR(C29="Blueprint Funded",C29="Pilot Funded",C29="Won"))),"WARN: Funded value stage mismatch","OK"))))))))))))))
A30: Hold | B30: Hold | C30: Hold | D30: Operations & Documents | E30: =IF(G30>=90,"A",IF(G30>=80,"B",IF(G30>=70,"C","D"))) | F30: Upwork:~022072326457921207805 | G30: 75 | H30: Upwork | I30: AI / Automation Engineer - Build an Automated Financial Data-to-Report Pipeline | J30: Hourly | K30: 50+ | L30: 4 weeks ago | M30: Financial data must move into a standardized report with analysis and QA instead of repeated manual assembly. | N30: One financial data source, one report template, and one QA checklist. | O30: I would build one repeatable data-to-report path first: one financial source, one standardized report, then QA checks before expanding. I packaged that exact pilot boundary here: https://dali.agents.ge/for/upwork/operations-docs?ref=uw-022072326457921207805 If that boundary matches your brief, reply here in Upwork with one representative input, the required output fields, the target system, and the exception owner. I will turn those inputs into the first replay set and pass/fail acceptance test before implementation. | P30: https://dali.agents.ge/for/upwork/operations-docs?ref=uw-022072326457921207805 | Q30: https://www.upwork.com/jobs/span-class-highlight-span-span-class-highlight-Automation-span-Engineer-Build-span-class-highlight-Automated-span-Financial-Data-Report-Pipeline_~022072326457921207805/?referrer_url_path=/nx/search/jobs/ | R30: Medium-high confidence; normalization and QA requirements are not fully specified. | T30: Unknown | X30: Not Evaluated | Y30: Hold | AE30: =IFERROR((AA30-AD30)/AA30,"") | AG30: Hold | AH30: Not Checked | AI30: Hold row; not part of the current live-listing audit. | AK30: =IF(AND(U30<>"",S30=""),"WARN: Reply date without sent date",IF(AND(OR(C30="Sent",C30="Replied",C30="Qualified",C30="Blueprint Proposed",C30="Pilot Proposed",C30="Blueprint Funded",C30="Pilot Funded",C30="Won"),S30=""),"WARN: Stage requires sent date",IF(AND(OR(C30="Replied",C30="Qualified",C30="Blueprint Proposed",C30="Pilot Proposed",C30="Blueprint Funded",C30="Pilot Funded",C30="Won"),U30=""),"WARN: Stage requires reply date",IF(AND(X30="Qualified",U30=""),"WARN: Qualified without reply date",IF(AND(C30="Qualified",X30<>"Qualified"),"WARN: Qualified stage mismatch",IF(AND(X30="Qualified",NOT(OR(C30="Qualified",C30="Blueprint Proposed",C30="Pilot Proposed",C30="Blueprint Funded",C30="Pilot Funded",C30="Won"))),"WARN: Qualified value stage mismatch",IF(AND(Z30>0,NOT(OR(Y30="Blueprint",Y30="Direct Pilot"))),"WARN: Quote without sales path",IF(AND(OR(C30="Blueprint Proposed",C30="Blueprint Funded"),Y30<>"Blueprint"),"WARN: Blueprint stage path mismatch",IF(AND(OR(C30="Pilot Proposed",C30="Pilot Funded"),Y30<>"Direct Pilot"),"WARN: Pilot stage path mismatch",IF(AND(OR(C30="Blueprint Proposed",C30="Pilot Proposed",C30="Blueprint Funded",C30="Pilot Funded",C30="Won"),Z30<=0),"WARN: Offer stage without quote",IF(AND(Z30>0,NOT(OR(C30="Blueprint Proposed",C30="Pilot Proposed",C30="Blueprint Funded",C30="Pilot Funded",C30="Won"))),"WARN: Quote stage mismatch",IF(AND(AA30>0,Z30<=0),"WARN: Funded without quote",IF(AND(OR(C30="Blueprint Funded",C30="Pilot Funded",C30="Won"),AA30<=0),"WARN: Funded stage without amount",IF(AND(AA30>0,NOT(OR(C30="Blueprint Funded",C30="Pilot Funded",C30="Won"))),"WARN: Funded value stage mismatch","OK"))))))))))))))
A31: Wave 1 | B31: Landing Link | C31: Not Sent | D31: Internal Knowledge Assistant | E31: =IF(G31>=90,"A",IF(G31>=80,"B",IF(G31>=70,"C","D"))) | F31: Upwork:~022075311922210730379 | G31: 90 | H31: Upwork | I31: AI Automation Engineer - Build One Business-Ops AI Agent (Claude + n8n, RAG) | J31: Hourly: $20.00 - $30.00 | K31: 50+ | L31: 3 weeks ago | M31: CRM, Sheets, and internal RAG documents must become a prioritized daily Slack briefing without unreliable autonomous actions. | N31: A read-only daily briefing from CRM, Sheets, and selected internal docs into one Slack list. | O31: You want CRM + Sheets + internal docs into a prioritized daily Slack briefing without unreliable autonomous actions. We already have a production-ready product core for this at Dali Agency (knowledge-assistant core): ingest approved sources → retrieve with citations → answer or refuse when evidence is missing → eval/replay set. We are not starting from a blank repo. The paid work is customization under your stack: your source bundle, user group, and refusal rules. First customization pilot I would lock: read-only daily briefing first: CRM + Sheets + selected docs → one prioritized Slack list; no autonomous writes until trusted. Packaged boundary + how we run that pilot: https://dali.agents.ge/for/upwork/knowledge-assistant?ref=uw-022075311922210730379 If that matches, reply here in Upwork with approved source set, intended users, and two real questions you ask today. I will confirm fit and send a fixed pilot milestone (or a short paid blueprint if scope is still loose) before any implementation starts. | P31: https://dali.agents.ge/for/upwork/knowledge-assistant?ref=uw-022075311922210730379 | Q31: https://www.upwork.com/jobs/span-class-highlight-span-span-class-highlight-Automation-span-Engineer-Build-One-Business-Ops-span-class-highlight-span-span-class-highlight-Agent-span-Claude-n8n-RAG_~022075311922210730379/?referrer_url_path=/nx/search/jobs/ | R31: High confidence; RAG quality and broad business-ops scope need a strict boundary. | T31: Unknown | X31: Not Evaluated | Y31: Unassigned | AE31: =IFERROR((AA31-AD31)/AA31,"") | AG31: Batch C | AH31: Manual Check | AI31: Anonymous direct page was blocked by a Cloudflare challenge. Verify open status and scope inside Upwork. | AJ31: 2026-07-30 03:14 +04 | AK31: =IF(AND(U31<>"",S31=""),"WARN: Reply date without sent date",IF(AND(OR(C31="Sent",C31="Replied",C31="Qualified",C31="Blueprint Proposed",C31="Pilot Proposed",C31="Blueprint Funded",C31="Pilot Funded",C31="Won"),S31=""),"WARN: Stage requires sent date",IF(AND(OR(C31="Replied",C31="Qualified",C31="Blueprint Proposed",C31="Pilot Proposed",C31="Blueprint Funded",C31="Pilot Funded",C31="Won"),U31=""),"WARN: Stage requires reply date",IF(AND(X31="Qualified",U31=""),"WARN: Qualified without reply date",IF(AND(C31="Qualified",X31<>"Qualified"),"WARN: Qualified stage mismatch",IF(AND(X31="Qualified",NOT(OR(C31="Qualified",C31="Blueprint Proposed",C31="Pilot Proposed",C31="Blueprint Funded",C31="Pilot Funded",C31="Won"))),"WARN: Qualified value stage mismatch",IF(AND(Z31>0,NOT(OR(Y31="Blueprint",Y31="Direct Pilot"))),"WARN: Quote without sales path",IF(AND(OR(C31="Blueprint Proposed",C31="Blueprint Funded"),Y31<>"Blueprint"),"WARN: Blueprint stage path mismatch",IF(AND(OR(C31="Pilot Proposed",C31="Pilot Funded"),Y31<>"Direct Pilot"),"WARN: Pilot stage path mismatch",IF(AND(OR(C31="Blueprint Proposed",C31="Pilot Proposed",C31="Blueprint Funded",C31="Pilot Funded",C31="Won"),Z31<=0),"WARN: Offer stage without quote",IF(AND(Z31>0,NOT(OR(C31="Blueprint Proposed",C31="Pilot Proposed",C31="Blueprint Funded",C31="Pilot Funded",C31="Won"))),"WARN: Quote stage mismatch",IF(AND(AA31>0,Z31<=0),"WARN: Funded without quote",IF(AND(OR(C31="Blueprint Funded",C31="Pilot Funded",C31="Won"),AA31<=0),"WARN: Funded stage without amount",IF(AND(AA31>0,NOT(OR(C31="Blueprint Funded",C31="Pilot Funded",C31="Won"))),"WARN: Funded value stage mismatch","OK"))))))))))))))
A32: Wave 1 | B32: Landing Link | C32: Lost | D32: Internal Knowledge Assistant | E32: =IF(G32>=90,"A",IF(G32>=80,"B",IF(G32>=70,"C","D"))) | F32: Upwork:~022082116475484824757 | G32: 80 | H32: Upwork | I32: Hive Second Brains: Shared Agentic Knowledge/Ontology Infrastructure + Graph RAG System | J32: Hourly: $50 | K32: 50+ | L32: 2 hours ago | M32: Shared knowledge across Slack, Notion, Zoom, and recordings must surface decisions, tasks, owners, deadlines, source links, and role-aware answers. | N32: Ingest two or three sources, extract decisions and tasks, add Slack search and source links; exclude Graph RAG, full RBAC, and 200-user scale claims. | O32: I saw your brief about a shared knowledge layer across Slack, Notion, Zoom, and meeting notes. I can scope a narrow pilot that extracts decisions, tasks, owners, and deadlines from a few sources, keeps answers grounded, and proves the workflow before any larger rollout. I packaged that exact pilot boundary here: https://dali.agents.ge/for/upwork/knowledge-assistant?ref=uw-022082116475484824757 If that boundary matches your brief, reply here in Upwork with the approved source set, intended users, and two representative questions. I will turn those inputs into the first replay set and pass/fail acceptance test before implementation. | P32: https://dali.agents.ge/for/upwork/knowledge-assistant?ref=uw-022082116475484824757 | Q32: https://www.upwork.com/jobs/Hive-Second-Brains-Shared-Agentic-Knowledge-Ontology-Infrastructure-Graph-RAG-System_~022082116475484824757/?referrer_url_path=find_work_home | R32: High confidence; scope can inflate into Graph RAG, enterprise RBAC, and 200-user scale before validation. | T32: Unknown | W32: Upwork reports the job is no longer available and activity shows one hire. Do not send. | X32: Not Evaluated | Y32: Archive | AB32: Role filled | AE32: =IFERROR((AA32-AD32)/AA32,"") | AG32: Skip - Closed | AH32: Closed | AI32: Upwork reports the job is no longer available and activity shows one hire. Do not send. | AJ32: 2026-07-30 03:17 +04 | AK32: =IF(AND(U32<>"",S32=""),"WARN: Reply date without sent date",IF(AND(OR(C32="Sent",C32="Replied",C32="Qualified",C32="Blueprint Proposed",C32="Pilot Proposed",C32="Blueprint Funded",C32="Pilot Funded",C32="Won"),S32=""),"WARN: Stage requires sent date",IF(AND(OR(C32="Replied",C32="Qualified",C32="Blueprint Proposed",C32="Pilot Proposed",C32="Blueprint Funded",C32="Pilot Funded",C32="Won"),U32=""),"WARN: Stage requires reply date",IF(AND(X32="Qualified",U32=""),"WARN: Qualified without reply date",IF(AND(C32="Qualified",X32<>"Qualified"),"WARN: Qualified stage mismatch",IF(AND(X32="Qualified",NOT(OR(C32="Qualified",C32="Blueprint Proposed",C32="Pilot Proposed",C32="Blueprint Funded",C32="Pilot Funded",C32="Won"))),"WARN: Qualified value stage mismatch",IF(AND(Z32>0,NOT(OR(Y32="Blueprint",Y32="Direct Pilot"))),"WARN: Quote without sales path",IF(AND(OR(C32="Blueprint Proposed",C32="Blueprint Funded"),Y32<>"Blueprint"),"WARN: Blueprint stage path mismatch",IF(AND(OR(C32="Pilot Proposed",C32="Pilot Funded"),Y32<>"Direct Pilot"),"WARN: Pilot stage path mismatch",IF(AND(OR(C32="Blueprint Proposed",C32="Pilot Proposed",C32="Blueprint Funded",C32="Pilot Funded",C32="Won"),Z32<=0),"WARN: Offer stage without quote",IF(AND(Z32>0,NOT(OR(C32="Blueprint Proposed",C32="Pilot Proposed",C32="Blueprint Funded",C32="Pilot Funded",C32="Won"))),"WARN: Quote stage mismatch",IF(AND(AA32>0,Z32<=0),"WARN: Funded without quote",IF(AND(OR(C32="Blueprint Funded",C32="Pilot Funded",C32="Won"),AA32<=0),"WARN: Funded stage without amount",IF(AND(AA32>0,NOT(OR(C32="Blueprint Funded",C32="Pilot Funded",C32="Won"))),"WARN: Funded value stage mismatch","OK"))))))))))))))
A33: Wave 1 | B33: Landing Link | C33: Not Sent | D33: Internal Knowledge Assistant | E33: =IF(G33>=90,"A",IF(G33>=80,"B",IF(G33>=70,"C","D"))) | F33: Upwork:~022081833254755580077 | G33: 75 | H33: Upwork | I33: RAG Chatbot Developer - LangChain + Vector Search over Internal Docs | J33: $500 | K33: 50+ | L33: 21 hours ago | M33: An internal-doc RAG chatbot must ship in 5-7 days with ingestion, chunking, vector search, source-linked answers, and fail-closed behavior. | N33: One document repository, explicit citations, and refusal when evidence is missing. | O33: 5-7 day internal-doc RAG chatbot with ingestion, vector search, source-linked answers, and fail-closed behavior. We already have a production-ready product core for this at Dali Agency (knowledge-assistant core): ingest approved sources → retrieve with citations → answer or refuse when evidence is missing → eval/replay set. We are not starting from a blank repo. The paid work is customization under your stack: your source bundle, user group, and refusal rules. First customization pilot I would lock: one document repository, citations on every factual answer, explicit refusal when evidence is missing. Packaged boundary + how we run that pilot: https://dali.agents.ge/for/upwork/knowledge-assistant?ref=uw-022081833254755580077 If that matches, reply here in Upwork with approved source set, intended users, and two real questions you ask today. I will confirm fit and send a fixed pilot milestone (or a short paid blueprint if scope is still loose) before any implementation starts. | P33: https://dali.agents.ge/for/upwork/knowledge-assistant?ref=uw-022081833254755580077 | Q33: https://www.upwork.com/jobs/RAG-Chatbot-Developer-LangChain-Vector-Search-over-Internal-Docs_~022081833254755580077/?referrer_url_path=find_work_home | R33: High confidence; proof of already shipped RAG systems matters more than feature breadth. | T33: Unknown | X33: Not Evaluated | Y33: Unassigned | AE33: =IFERROR((AA33-AD33)/AA33,"") | AG33: Batch B | AH33: Manual Check | AI33: Anonymous direct page was blocked by a Cloudflare challenge. Verify open status and scope inside Upwork. | AJ33: 2026-07-30 03:13 +04 | AK33: =IF(AND(U33<>"",S33=""),"WARN: Reply date without sent date",IF(AND(OR(C33="Sent",C33="Replied",C33="Qualified",C33="Blueprint Proposed",C33="Pilot Proposed",C33="Blueprint Funded",C33="Pilot Funded",C33="Won"),S33=""),"WARN: Stage requires sent date",IF(AND(OR(C33="Replied",C33="Qualified",C33="Blueprint Proposed",C33="Pilot Proposed",C33="Blueprint Funded",C33="Pilot Funded",C33="Won"),U33=""),"WARN: Stage requires reply date",IF(AND(X33="Qualified",U33=""),"WARN: Qualified without reply date",IF(AND(C33="Qualified",X33<>"Qualified"),"WARN: Qualified stage mismatch",IF(AND(X33="Qualified",NOT(OR(C33="Qualified",C33="Blueprint Proposed",C33="Pilot Proposed",C33="Blueprint Funded",C33="Pilot Funded",C33="Won"))),"WARN: Qualified value stage mismatch",IF(AND(Z33>0,NOT(OR(Y33="Blueprint",Y33="Direct Pilot"))),"WARN: Quote without sales path",IF(AND(OR(C33="Blueprint Proposed",C33="Blueprint Funded"),Y33<>"Blueprint"),"WARN: Blueprint stage path mismatch",IF(AND(OR(C33="Pilot Proposed",C33="Pilot Funded"),Y33<>"Direct Pilot"),"WARN: Pilot stage path mismatch",IF(AND(OR(C33="Blueprint Proposed",C33="Pilot Proposed",C33="Blueprint Funded",C33="Pilot Funded",C33="Won"),Z33<=0),"WARN: Offer stage without quote",IF(AND(Z33>0,NOT(OR(C33="Blueprint Proposed",C33="Pilot Proposed",C33="Blueprint Funded",C33="Pilot Funded",C33="Won"))),"WARN: Quote stage mismatch",IF(AND(AA33>0,Z33<=0),"WARN: Funded without quote",IF(AND(OR(C33="Blueprint Funded",C33="Pilot Funded",C33="Won"),AA33<=0),"WARN: Funded stage without amount",IF(AND(AA33>0,NOT(OR(C33="Blueprint Funded",C33="Pilot Funded",C33="Won"))),"WARN: Funded value stage mismatch","OK"))))))))))))))
A34: Wave 1 | B34: No-Link Diagnostic | C34: Not Sent | D34: Internal Knowledge Assistant | E34: =IF(G34>=90,"A",IF(G34>=80,"B",IF(G34>=70,"C","D"))) | F34: Upwork:~022079236014340896590 | G34: 75 | H34: Upwork | I34: AI Agent Developer (Python/FastAPI) - RAG, Pinecone & LLM Automation Expert Needed | J34: Hourly: $25.00 - $50.00 | K34: 50+ | L34: last week | M34: A production RAG system needs ingestion, chunking, embeddings, Pinecone hybrid search, tools, memory, evaluation, observability, and deployment. | N34: One ingestion-to-answer loop, one vector store, one tool path, and basic evaluation logs. | O34: Production RAG with ingestion, Pinecone hybrid search, tools, memory, eval, and deployment is a full system - start by proving the answer loop. We already have a production-ready product core for this at Dali Agency (knowledge-assistant core): ingest approved sources → retrieve with citations → answer or refuse when evidence is missing → eval/replay set. We are not starting from a blank repo. The paid work is customization under your stack: your source bundle, user group, and refusal rules. First customization pilot I would lock: one ingestion-to-answer loop, one vector store, one tool path, basic evaluation logs before memory/multi-tool expansion. If that matches, reply here in Upwork with approved source set, intended users, and two real questions you ask today. I will confirm fit and send a fixed pilot milestone (or a short paid blueprint if scope is still loose) before any implementation starts. | P34: No link in diagnostic proposal | Q34: https://www.upwork.com/jobs/span-class-highlight-span-span-class-highlight-Agent-span-Developer-Python-FastAPI-RAG-Pinecone-amp-LLM-span-class-highlight-Automation-span-Expert-Needed_~022079236014340896590/?referrer_url_path=/nx/search/jobs/ | R34: Medium-high confidence; the ask includes a larger agent platform, not only a knowledge assistant. | T34: Unknown | X34: Not Evaluated | Y34: Unassigned | AE34: =IFERROR((AA34-AD34)/AA34,"") | AG34: Batch C | AH34: Manual Check | AI34: Anonymous direct page was blocked by a Cloudflare challenge. Verify open status and scope inside Upwork before the no-link diagnostic. | AJ34: 2026-07-30 03:14 +04 | AK34: =IF(AND(U34<>"",S34=""),"WARN: Reply date without sent date",IF(AND(OR(C34="Sent",C34="Replied",C34="Qualified",C34="Blueprint Proposed",C34="Pilot Proposed",C34="Blueprint Funded",C34="Pilot Funded",C34="Won"),S34=""),"WARN: Stage requires sent date",IF(AND(OR(C34="Replied",C34="Qualified",C34="Blueprint Proposed",C34="Pilot Proposed",C34="Blueprint Funded",C34="Pilot Funded",C34="Won"),U34=""),"WARN: Stage requires reply date",IF(AND(X34="Qualified",U34=""),"WARN: Qualified without reply date",IF(AND(C34="Qualified",X34<>"Qualified"),"WARN: Qualified stage mismatch",IF(AND(X34="Qualified",NOT(OR(C34="Qualified",C34="Blueprint Proposed",C34="Pilot Proposed",C34="Blueprint Funded",C34="Pilot Funded",C34="Won"))),"WARN: Qualified value stage mismatch",IF(AND(Z34>0,NOT(OR(Y34="Blueprint",Y34="Direct Pilot"))),"WARN: Quote without sales path",IF(AND(OR(C34="Blueprint Proposed",C34="Blueprint Funded"),Y34<>"Blueprint"),"WARN: Blueprint stage path mismatch",IF(AND(OR(C34="Pilot Proposed",C34="Pilot Funded"),Y34<>"Direct Pilot"),"WARN: Pilot stage path mismatch",IF(AND(OR(C34="Blueprint Proposed",C34="Pilot Proposed",C34="Blueprint Funded",C34="Pilot Funded",C34="Won"),Z34<=0),"WARN: Offer stage without quote",IF(AND(Z34>0,NOT(OR(C34="Blueprint Proposed",C34="Pilot Proposed",C34="Blueprint Funded",C34="Pilot Funded",C34="Won"))),"WARN: Quote stage mismatch",IF(AND(AA34>0,Z34<=0),"WARN: Funded without quote",IF(AND(OR(C34="Blueprint Funded",C34="Pilot Funded",C34="Won"),AA34<=0),"WARN: Funded stage without amount",IF(AND(AA34>0,NOT(OR(C34="Blueprint Funded",C34="Pilot Funded",C34="Won"))),"WARN: Funded value stage mismatch","OK"))))))))))))))
A35: Hold | B35: Hold | C35: Hold | D35: Internal Knowledge Assistant | E35: =IF(G35>=90,"A",IF(G35>=80,"B",IF(G35>=70,"C","D"))) | F35: Upwork:~022081922819151747063 | G35: 70 | H35: Upwork | I35: AI Knowledge Assistant for AML/CTF Compliance Platform (Sydney Preferred) | J35: $1,500 | K35: 50+ | L35: 15 hours ago | M35: A compliance assistant must answer from AUSTRAC, legislation, SOPs, and industry rules for multiple client types with precise context. | N35: One client type, one curated source set, citation-backed answers, and strict refusal outside approved material. | O35: I read your compliance assistant brief and would treat it as a narrow, controlled knowledge assistant pilot. The safest path is one client type, one curated source set, citation-backed answers, and a strict refusal mode for anything outside the approved material. I packaged that exact pilot boundary here: https://dali.agents.ge/for/upwork/knowledge-assistant?ref=uw-022081922819151747063 If that boundary matches your brief, reply here in Upwork with the approved source set, intended users, and two representative questions. I will turn those inputs into the first replay set and pass/fail acceptance test before implementation. | P35: https://dali.agents.ge/for/upwork/knowledge-assistant?ref=uw-022081922819151747063 | Q35: https://www.upwork.com/jobs/Knowledge-Assistant-for-AML-CTF-Compliance-Platform-Sydney-Preferred_~022081922819151747063/?referrer_url_path=find_work_home | R35: High confidence; legal sensitivity, Sydney preference, and a short timeline make overpromising risky. | T35: Unknown | X35: Not Evaluated | Y35: Hold | AE35: =IFERROR((AA35-AD35)/AA35,"") | AG35: Hold | AH35: Not Checked | AI35: Hold row; not part of the current live-listing audit. | AK35: =IF(AND(U35<>"",S35=""),"WARN: Reply date without sent date",IF(AND(OR(C35="Sent",C35="Replied",C35="Qualified",C35="Blueprint Proposed",C35="Pilot Proposed",C35="Blueprint Funded",C35="Pilot Funded",C35="Won"),S35=""),"WARN: Stage requires sent date",IF(AND(OR(C35="Replied",C35="Qualified",C35="Blueprint Proposed",C35="Pilot Proposed",C35="Blueprint Funded",C35="Pilot Funded",C35="Won"),U35=""),"WARN: Stage requires reply date",IF(AND(X35="Qualified",U35=""),"WARN: Qualified without reply date",IF(AND(C35="Qualified",X35<>"Qualified"),"WARN: Qualified stage mismatch",IF(AND(X35="Qualified",NOT(OR(C35="Qualified",C35="Blueprint Proposed",C35="Pilot Proposed",C35="Blueprint Funded",C35="Pilot Funded",C35="Won"))),"WARN: Qualified value stage mismatch",IF(AND(Z35>0,NOT(OR(Y35="Blueprint",Y35="Direct Pilot"))),"WARN: Quote without sales path",IF(AND(OR(C35="Blueprint Proposed",C35="Blueprint Funded"),Y35<>"Blueprint"),"WARN: Blueprint stage path mismatch",IF(AND(OR(C35="Pilot Proposed",C35="Pilot Funded"),Y35<>"Direct Pilot"),"WARN: Pilot stage path mismatch",IF(AND(OR(C35="Blueprint Proposed",C35="Pilot Proposed",C35="Blueprint Funded",C35="Pilot Funded",C35="Won"),Z35<=0),"WARN: Offer stage without quote",IF(AND(Z35>0,NOT(OR(C35="Blueprint Proposed",C35="Pilot Proposed",C35="Blueprint Funded",C35="Pilot Funded",C35="Won"))),"WARN: Quote stage mismatch",IF(AND(AA35>0,Z35<=0),"WARN: Funded without quote",IF(AND(OR(C35="Blueprint Funded",C35="Pilot Funded",C35="Won"),AA35<=0),"WARN: Funded stage without amount",IF(AND(AA35>0,NOT(OR(C35="Blueprint Funded",C35="Pilot Funded",C35="Won"))),"WARN: Funded value stage mismatch","OK"))))))))))))))
A36: Hold | B36: Design Partner Hold | C36: Hold | D36: Voice Agents | E36: =IF(G36>=90,"A",IF(G36>=80,"B",IF(G36>=70,"C","D"))) | F36: Upwork:~022082043668763252124 | G36: 65 | H36: Upwork | I36: AI Automation | AI Voice Agent & n8n Automation | Vapi / Retell AI / Eleven Labs | LLM Integration | J36: Hourly: $20-$40 | K36: 50+ | L36: 7 hours ago | M36: Voice agents across Vapi, Retell, and ElevenLabs must answer calls, qualify, book, support, and update CRM and calendar through automation. | N36: One disclosed inbound call flow, one booking or qualification path, and human transfer outside scope. | O36: Your brief fits a narrow pilot well: one disclosed inbound call flow, one booking or qualification path, and human transfer for exceptions. I would avoid expanding into support and multiple channels until the first lane is reliable. I packaged that exact pilot boundary here: https://dali.agents.ge/for/upwork/voice-agents?ref=uw-022082043668763252124 If that boundary matches your brief, reply here in Upwork with one call type, telephony provider, intended action, and human handoff rule. I will turn those inputs into the first replay set and pass/fail acceptance test before implementation. | P36: https://dali.agents.ge/for/upwork/voice-agents?ref=uw-022082043668763252124 | Q36: https://www.upwork.com/jobs/Automation-Voice-Agent-n8n-Automation-Vapi-Retell-Eleven-Labs-LLM-Integration_~022082043668763252124/?referrer_url_path=find_work_home | R36: Medium-high confidence; scope is broad, though the hourly rate is plausible. | T36: Unknown | X36: Not Evaluated | Y36: Hold | AE36: =IFERROR((AA36-AD36)/AA36,"") | AG36: Hold | AH36: Not Checked | AI36: Hold row; not part of the current live-listing audit. | AK36: =IF(AND(U36<>"",S36=""),"WARN: Reply date without sent date",IF(AND(OR(C36="Sent",C36="Replied",C36="Qualified",C36="Blueprint Proposed",C36="Pilot Proposed",C36="Blueprint Funded",C36="Pilot Funded",C36="Won"),S36=""),"WARN: Stage requires sent date",IF(AND(OR(C36="Replied",C36="Qualified",C36="Blueprint Proposed",C36="Pilot Proposed",C36="Blueprint Funded",C36="Pilot Funded",C36="Won"),U36=""),"WARN: Stage requires reply date",IF(AND(X36="Qualified",U36=""),"WARN: Qualified without reply date",IF(AND(C36="Qualified",X36<>"Qualified"),"WARN: Qualified stage mismatch",IF(AND(X36="Qualified",NOT(OR(C36="Qualified",C36="Blueprint Proposed",C36="Pilot Proposed",C36="Blueprint Funded",C36="Pilot Funded",C36="Won"))),"WARN: Qualified value stage mismatch",IF(AND(Z36>0,NOT(OR(Y36="Blueprint",Y36="Direct Pilot"))),"WARN: Quote without sales path",IF(AND(OR(C36="Blueprint Proposed",C36="Blueprint Funded"),Y36<>"Blueprint"),"WARN: Blueprint stage path mismatch",IF(AND(OR(C36="Pilot Proposed",C36="Pilot Funded"),Y36<>"Direct Pilot"),"WARN: Pilot stage path mismatch",IF(AND(OR(C36="Blueprint Proposed",C36="Pilot Proposed",C36="Blueprint Funded",C36="Pilot Funded",C36="Won"),Z36<=0),"WARN: Offer stage without quote",IF(AND(Z36>0,NOT(OR(C36="Blueprint Proposed",C36="Pilot Proposed",C36="Blueprint Funded",C36="Pilot Funded",C36="Won"))),"WARN: Quote stage mismatch",IF(AND(AA36>0,Z36<=0),"WARN: Funded without quote",IF(AND(OR(C36="Blueprint Funded",C36="Pilot Funded",C36="Won"),AA36<=0),"WARN: Funded stage without amount",IF(AND(AA36>0,NOT(OR(C36="Blueprint Funded",C36="Pilot Funded",C36="Won"))),"WARN: Funded value stage mismatch","OK"))))))))))))))
A37: Hold | B37: Design Partner Hold | C37: Hold | D37: Voice Agents | E37: =IF(G37>=90,"A",IF(G37>=80,"B",IF(G37>=70,"C","D"))) | F37: Upwork:~022080259272497837564 | G37: 65 | H37: Upwork | I37: AI Calling Agent & AI Chatbot Developer for Business Automation | J37: Hourly: $25.00 - $40.00 | K37: 20 to 50 | L37: 5 days ago | M37: One phone agent plus chatbot must connect CRM, calendar, knowledge base, analytics, and production deployment, but evaluation is unclear. | N37: Voice-first on one call type, one CRM update, one handoff path; defer chat. | O37: I would separate this into a voice-first pilot instead of building the phone agent and chatbot together. One call type, one CRM update, and one handoff path is the safest way to prove the system before expanding. I packaged that exact pilot boundary here: https://dali.agents.ge/for/upwork/voice-agents?ref=uw-022080259272497837564 If that boundary matches your brief, reply here in Upwork with one call type, telephony provider, intended action, and human handoff rule. I will turn those inputs into the first replay set and pass/fail acceptance test before implementation. | P37: https://dali.agents.ge/for/upwork/voice-agents?ref=uw-022080259272497837564 | Q37: https://www.upwork.com/jobs/span-class-highlight-span-Calling-span-class-highlight-Agent-span-amp-span-class-highlight-span-Chatbot-Developer-for-Business-span-class-highlight-Automation-span_~022080259272497837564/?referrer_url_path=/nx/search/jobs/ | R37: High confidence; combined voice and chat scope must stay narrow. | T37: Unknown | X37: Not Evaluated | Y37: Hold | AE37: =IFERROR((AA37-AD37)/AA37,"") | AG37: Hold | AH37: Not Checked | AI37: Hold row; not part of the current live-listing audit. | AK37: =IF(AND(U37<>"",S37=""),"WARN: Reply date without sent date",IF(AND(OR(C37="Sent",C37="Replied",C37="Qualified",C37="Blueprint Proposed",C37="Pilot Proposed",C37="Blueprint Funded",C37="Pilot Funded",C37="Won"),S37=""),"WARN: Stage requires sent date",IF(AND(OR(C37="Replied",C37="Qualified",C37="Blueprint Proposed",C37="Pilot Proposed",C37="Blueprint Funded",C37="Pilot Funded",C37="Won"),U37=""),"WARN: Stage requires reply date",IF(AND(X37="Qualified",U37=""),"WARN: Qualified without reply date",IF(AND(C37="Qualified",X37<>"Qualified"),"WARN: Qualified stage mismatch",IF(AND(X37="Qualified",NOT(OR(C37="Qualified",C37="Blueprint Proposed",C37="Pilot Proposed",C37="Blueprint Funded",C37="Pilot Funded",C37="Won"))),"WARN: Qualified value stage mismatch",IF(AND(Z37>0,NOT(OR(Y37="Blueprint",Y37="Direct Pilot"))),"WARN: Quote without sales path",IF(AND(OR(C37="Blueprint Proposed",C37="Blueprint Funded"),Y37<>"Blueprint"),"WARN: Blueprint stage path mismatch",IF(AND(OR(C37="Pilot Proposed",C37="Pilot Funded"),Y37<>"Direct Pilot"),"WARN: Pilot stage path mismatch",IF(AND(OR(C37="Blueprint Proposed",C37="Pilot Proposed",C37="Blueprint Funded",C37="Pilot Funded",C37="Won"),Z37<=0),"WARN: Offer stage without quote",IF(AND(Z37>0,NOT(OR(C37="Blueprint Proposed",C37="Pilot Proposed",C37="Blueprint Funded",C37="Pilot Funded",C37="Won"))),"WARN: Quote stage mismatch",IF(AND(AA37>0,Z37<=0),"WARN: Funded without quote",IF(AND(OR(C37="Blueprint Funded",C37="Pilot Funded",C37="Won"),AA37<=0),"WARN: Funded stage without amount",IF(AND(AA37>0,NOT(OR(C37="Blueprint Funded",C37="Pilot Funded",C37="Won"))),"WARN: Funded value stage mismatch","OK"))))))))))))))

Sheet Dashboard
A1: Dali marketplace presale launch
A3: A live control panel for the 32 selected marketplace requests. Update only the pale-yellow cells in Outreach Queue; formulas and this dashboard update automatically.
A5: Total targets | C5: Original Wave 1 | E5: Current sendable | G5: Current linked | I5: No-link diagnostic | K5: Holds
A6: =COUNTA('Outreach Queue'!$F$6:$F$37) | C6: =COUNTIF('Outreach Queue'!$A$6:$A$37,"Wave 1") | E6: =COUNTIFS('Outreach Queue'!$A$6:$A$37,"Wave 1",'Outreach Queue'!$AG$6:$AG$37,"<>Skip - Closed",'Outreach Queue'!$AH$6:$AH$37,"<>Closed") | G6: =COUNTIFS('Outreach Queue'!$A$6:$A$37,"Wave 1",'Outreach Queue'!$B$6:$B$37,"Landing Link",'Outreach Queue'!$AG$6:$AG$37,"<>Skip - Closed",'Outreach Queue'!$AH$6:$AH$37,"<>Closed") | I6: =COUNTIFS('Outreach Queue'!$A$6:$A$37,"Wave 1",'Outreach Queue'!$B$6:$B$37,"No-Link Diagnostic",'Outreach Queue'!$AG$6:$AG$37,"<>Skip - Closed",'Outreach Queue'!$AH$6:$AH$37,"<>Closed") | K6: =COUNTIF('Outreach Queue'!$C$6:$C$37,"Hold")
A7: selected | C7: planned | E7: maximum now | G7: sendable | I7: not causal | K7: not sent
A10: Live funnel | E10: Current stage distribution | I10: Current dispatch state
A11: Event | B11: Current | C11: Rate vs sent | D11: Conditional rate | E11: Stage | F11: Count | I11: Variant | J11: Count
A12: Proposals sent | B12: =COUNT('Outreach Queue'!$S$6:$S$37) | C12: =IFERROR(B12/$E$6,0) | D12: ="" | E12: Not Sent | F12: =COUNTIF('Outreach Queue'!$C$6:$C$37,"Not Sent") | I12: Landing Link - Sendable | J12: =COUNTIFS('Outreach Queue'!$A$6:$A$37,"Wave 1",'Outreach Queue'!$B$6:$B$37,"Landing Link",'Outreach Queue'!$AG$6:$AG$37,"<>Skip - Closed",'Outreach Queue'!$AH$6:$AH$37,"<>Closed")
A13: Page viewed | B13: =COUNTIF('Outreach Queue'!$T$6:$T$37,"Yes") | C13: =IFERROR(B13/$B$12,0) | D13: =IFERROR(B13/B12,0) | E13: Sent | F13: =COUNTIF('Outreach Queue'!$C$6:$C$37,"Sent") | I13: No-Link Diagnostic | J13: =COUNTIFS('Outreach Queue'!$A$6:$A$37,"Wave 1",'Outreach Queue'!$B$6:$B$37,"No-Link Diagnostic",'Outreach Queue'!$AG$6:$AG$37,"<>Skip - Closed",'Outreach Queue'!$AH$6:$AH$37,"<>Closed")
A14: Reply received | B14: =COUNT('Outreach Queue'!$U$6:$U$37) | C14: =IFERROR(B14/$B$12,0) | D14: =IFERROR(B14/B12,0) | E14: Replied | F14: =COUNTIF('Outreach Queue'!$C$6:$C$37,"Replied") | I14: Hold | J14: =COUNTIF('Outreach Queue'!$B$6:$B$37,"Hold")
A15: Qualified | B15: =COUNTIF('Outreach Queue'!$X$6:$X$37,"Qualified") | C15: =IFERROR(B15/$B$12,0) | D15: =IFERROR(B15/B14,0) | E15: Qualified | F15: =COUNTIF('Outreach Queue'!$C$6:$C$37,"Qualified") | I15: Design Partner Hold | J15: =COUNTIF('Outreach Queue'!$B$6:$B$37,"Design Partner Hold")
A16: Blueprint proposed | B16: =COUNTIFS('Outreach Queue'!$Y$6:$Y$37,"Blueprint",'Outreach Queue'!$Z$6:$Z$37,">0") | C16: =IFERROR(B16/$B$12,0) | D16: =IFERROR(B16/B15,0) | E16: Blueprint Proposed | F16: =COUNTIF('Outreach Queue'!$C$6:$C$37,"Blueprint Proposed") | I16: Skip - Closed | J16: =COUNTIF('Outreach Queue'!$AG$6:$AG$37,"Skip - Closed")
A17: Pilot proposed | B17: =COUNTIFS('Outreach Queue'!$Y$6:$Y$37,"Direct Pilot",'Outreach Queue'!$Z$6:$Z$37,">0") | C17: =IFERROR(B17/$B$12,0) | D17: =IFERROR(B17/B15,0) | E17: Pilot Proposed | F17: =COUNTIF('Outreach Queue'!$C$6:$C$37,"Pilot Proposed")
A18: Funded milestone | B18: =COUNTIF('Outreach Queue'!$AA$6:$AA$37,">0") | C18: =IFERROR(B18/$B$12,0) | D18: =IFERROR(B18/B14,0) | E18: Blueprint Funded | F18: =COUNTIF('Outreach Queue'!$C$6:$C$37,"Blueprint Funded")
A19: Won contract | B19: =COUNTIF('Outreach Queue'!$C$6:$C$37,"Won") | C19: =IFERROR(B19/$B$12,0) | D19: =IFERROR(B19/B18,0) | E19: Pilot Funded | F19: =COUNTIF('Outreach Queue'!$C$6:$C$37,"Pilot Funded")
E20: Won | F20: =COUNTIF('Outreach Queue'!$C$6:$C$37,"Won")
E21: Lost | F21: =COUNTIF('Outreach Queue'!$C$6:$C$37,"Lost")
E22: Hold | F22: =COUNTIF('Outreach Queue'!$C$6:$C$37,"Hold")
A24: ="Live listing audit: "&COUNTIF('Outreach Queue'!$AH$6:$AH$37,"Open")&" open, "&COUNTIF('Outreach Queue'!$AH$6:$AH$37,"Manual Check")&" manual checks, "&COUNTIF('Outreach Queue'!$AH$6:$AH$37,"Closed")&" closed. Data integrity: "&COUNTIF('Outreach Queue'!$AK$6:$AK$37,"WARN:*")&" warnings. Voice Agents remains research and design-partner only."
A27: Wave 1 category commercial evidence
A28: Group | B28: Selected | C28: Sendable | D28: Sent | E28: Replied | F28: Qualified | G28: Blueprint offered | H28: Pilot offered | I28: Funded | J28: Won | K28: Selected avg | L28: Evidence status
A29: Lead Response | B29: =COUNTIF('Outreach Queue'!$D$6:$D$37,"Lead Response") | C29: =COUNTIFS('Outreach Queue'!$D$6:$D$37,"Lead Response",'Outreach Queue'!$A$6:$A$37,"Wave 1",'Outreach Queue'!$AG$6:$AG$37,"<>Skip - Closed",'Outreach Queue'!$AH$6:$AH$37,"<>Closed") | D29: =COUNTIFS('Outreach Queue'!$D$6:$D$37,"Lead Response",'Outreach Queue'!$A$6:$A$37,"Wave 1",'Outreach Queue'!$AG$6:$AG$37,"<>Skip - Closed",'Outreach Queue'!$S$6:$S$37,"<>") | E29: =COUNTIFS('Outreach Queue'!$D$6:$D$37,"Lead Response",'Outreach Queue'!$A$6:$A$37,"Wave 1",'Outreach Queue'!$AG$6:$AG$37,"<>Skip - Closed",'Outreach Queue'!$U$6:$U$37,"<>") | F29: =COUNTIFS('Outreach Queue'!$D$6:$D$37,"Lead Response",'Outreach Queue'!$A$6:$A$37,"Wave 1",'Outreach Queue'!$AG$6:$AG$37,"<>Skip - Closed",'Outreach Queue'!$X$6:$X$37,"Qualified") | G29: =COUNTIFS('Outreach Queue'!$D$6:$D$37,"Lead Response",'Outreach Queue'!$A$6:$A$37,"Wave 1",'Outreach Queue'!$AG$6:$AG$37,"<>Skip - Closed",'Outreach Queue'!$Y$6:$Y$37,"Blueprint",'Outreach Queue'!$Z$6:$Z$37,">0") | H29: =COUNTIFS('Outreach Queue'!$D$6:$D$37,"Lead Response",'Outreach Queue'!$A$6:$A$37,"Wave 1",'Outreach Queue'!$AG$6:$AG$37,"<>Skip - Closed",'Outreach Queue'!$Y$6:$Y$37,"Direct Pilot",'Outreach Queue'!$Z$6:$Z$37,">0") | I29: =COUNTIFS('Outreach Queue'!$D$6:$D$37,"Lead Response",'Outreach Queue'!$A$6:$A$37,"Wave 1",'Outreach Queue'!$AG$6:$AG$37,"<>Skip - Closed",'Outreach Queue'!$AA$6:$AA$37,">0") | J29: =COUNTIFS('Outreach Queue'!$D$6:$D$37,"Lead Response",'Outreach Queue'!$A$6:$A$37,"Wave 1",'Outreach Queue'!$AG$6:$AG$37,"<>Skip - Closed",'Outreach Queue'!$C$6:$C$37,"Won") | K29: =IFERROR(AVERAGEIF('Outreach Queue'!$D$6:$D$37,"Lead Response",'Outreach Queue'!$G$6:$G$37),0) | L29: =IF(OR(I29>=1,F29>=2),"Promising - replicate","Unproven")
A30: Client Inbox | B30: =COUNTIF('Outreach Queue'!$D$6:$D$37,"Client Inbox") | C30: =COUNTIFS('Outreach Queue'!$D$6:$D$37,"Client Inbox",'Outreach Queue'!$A$6:$A$37,"Wave 1",'Outreach Queue'!$AG$6:$AG$37,"<>Skip - Closed",'Outreach Queue'!$AH$6:$AH$37,"<>Closed") | D30: =COUNTIFS('Outreach Queue'!$D$6:$D$37,"Client Inbox",'Outreach Queue'!$A$6:$A$37,"Wave 1",'Outreach Queue'!$AG$6:$AG$37,"<>Skip - Closed",'Outreach Queue'!$S$6:$S$37,"<>") | E30: =COUNTIFS('Outreach Queue'!$D$6:$D$37,"Client Inbox",'Outreach Queue'!$A$6:$A$37,"Wave 1",'Outreach Queue'!$AG$6:$AG$37,"<>Skip - Closed",'Outreach Queue'!$U$6:$U$37,"<>") | F30: =COUNTIFS('Outreach Queue'!$D$6:$D$37,"Client Inbox",'Outreach Queue'!$A$6:$A$37,"Wave 1",'Outreach Queue'!$AG$6:$AG$37,"<>Skip - Closed",'Outreach Queue'!$X$6:$X$37,"Qualified") | G30: =COUNTIFS('Outreach Queue'!$D$6:$D$37,"Client Inbox",'Outreach Queue'!$A$6:$A$37,"Wave 1",'Outreach Queue'!$AG$6:$AG$37,"<>Skip - Closed",'Outreach Queue'!$Y$6:$Y$37,"Blueprint",'Outreach Queue'!$Z$6:$Z$37,">0") | H30: =COUNTIFS('Outreach Queue'!$D$6:$D$37,"Client Inbox",'Outreach Queue'!$A$6:$A$37,"Wave 1",'Outreach Queue'!$AG$6:$AG$37,"<>Skip - Closed",'Outreach Queue'!$Y$6:$Y$37,"Direct Pilot",'Outreach Queue'!$Z$6:$Z$37,">0") | I30: =COUNTIFS('Outreach Queue'!$D$6:$D$37,"Client Inbox",'Outreach Queue'!$A$6:$A$37,"Wave 1",'Outreach Queue'!$AG$6:$AG$37,"<>Skip - Closed",'Outreach Queue'!$AA$6:$AA$37,">0") | J30: =COUNTIFS('Outreach Queue'!$D$6:$D$37,"Client Inbox",'Outreach Queue'!$A$6:$A$37,"Wave 1",'Outreach Queue'!$AG$6:$AG$37,"<>Skip - Closed",'Outreach Queue'!$C$6:$C$37,"Won") | K30: =IFERROR(AVERAGEIF('Outreach Queue'!$D$6:$D$37,"Client Inbox",'Outreach Queue'!$G$6:$G$37),0) | L30: =IF(OR(I30>=1,F30>=2),"Promising - replicate","Unproven")
A31: Operations & Documents | B31: =COUNTIF('Outreach Queue'!$D$6:$D$37,"Operations & Documents") | C31: =COUNTIFS('Outreach Queue'!$D$6:$D$37,"Operations & Documents",'Outreach Queue'!$A$6:$A$37,"Wave 1",'Outreach Queue'!$AG$6:$AG$37,"<>Skip - Closed",'Outreach Queue'!$AH$6:$AH$37,"<>Closed") | D31: =COUNTIFS('Outreach Queue'!$D$6:$D$37,"Operations & Documents",'Outreach Queue'!$A$6:$A$37,"Wave 1",'Outreach Queue'!$AG$6:$AG$37,"<>Skip - Closed",'Outreach Queue'!$S$6:$S$37,"<>") | E31: =COUNTIFS('Outreach Queue'!$D$6:$D$37,"Operations & Documents",'Outreach Queue'!$A$6:$A$37,"Wave 1",'Outreach Queue'!$AG$6:$AG$37,"<>Skip - Closed",'Outreach Queue'!$U$6:$U$37,"<>") | F31: =COUNTIFS('Outreach Queue'!$D$6:$D$37,"Operations & Documents",'Outreach Queue'!$A$6:$A$37,"Wave 1",'Outreach Queue'!$AG$6:$AG$37,"<>Skip - Closed",'Outreach Queue'!$X$6:$X$37,"Qualified") | G31: =COUNTIFS('Outreach Queue'!$D$6:$D$37,"Operations & Documents",'Outreach Queue'!$A$6:$A$37,"Wave 1",'Outreach Queue'!$AG$6:$AG$37,"<>Skip - Closed",'Outreach Queue'!$Y$6:$Y$37,"Blueprint",'Outreach Queue'!$Z$6:$Z$37,">0") | H31: =COUNTIFS('Outreach Queue'!$D$6:$D$37,"Operations & Documents",'Outreach Queue'!$A$6:$A$37,"Wave 1",'Outreach Queue'!$AG$6:$AG$37,"<>Skip - Closed",'Outreach Queue'!$Y$6:$Y$37,"Direct Pilot",'Outreach Queue'!$Z$6:$Z$37,">0") | I31: =COUNTIFS('Outreach Queue'!$D$6:$D$37,"Operations & Documents",'Outreach Queue'!$A$6:$A$37,"Wave 1",'Outreach Queue'!$AG$6:$AG$37,"<>Skip - Closed",'Outreach Queue'!$AA$6:$AA$37,">0") | J31: =COUNTIFS('Outreach Queue'!$D$6:$D$37,"Operations & Documents",'Outreach Queue'!$A$6:$A$37,"Wave 1",'Outreach Queue'!$AG$6:$AG$37,"<>Skip - Closed",'Outreach Queue'!$C$6:$C$37,"Won") | K31: =IFERROR(AVERAGEIF('Outreach Queue'!$D$6:$D$37,"Operations & Documents",'Outreach Queue'!$G$6:$G$37),0) | L31: =IF(OR(I31>=1,F31>=2),"Promising - replicate","Unproven")
A32: Internal Knowledge Assistant | B32: =COUNTIF('Outreach Queue'!$D$6:$D$37,"Internal Knowledge Assistant") | C32: =COUNTIFS('Outreach Queue'!$D$6:$D$37,"Internal Knowledge Assistant",'Outreach Queue'!$A$6:$A$37,"Wave 1",'Outreach Queue'!$AG$6:$AG$37,"<>Skip - Closed",'Outreach Queue'!$AH$6:$AH$37,"<>Closed") | D32: =COUNTIFS('Outreach Queue'!$D$6:$D$37,"Internal Knowledge Assistant",'Outreach Queue'!$A$6:$A$37,"Wave 1",'Outreach Queue'!$AG$6:$AG$37,"<>Skip - Closed",'Outreach Queue'!$S$6:$S$37,"<>") | E32: =COUNTIFS('Outreach Queue'!$D$6:$D$37,"Internal Knowledge Assistant",'Outreach Queue'!$A$6:$A$37,"Wave 1",'Outreach Queue'!$AG$6:$AG$37,"<>Skip - Closed",'Outreach Queue'!$U$6:$U$37,"<>") | F32: =COUNTIFS('Outreach Queue'!$D$6:$D$37,"Internal Knowledge Assistant",'Outreach Queue'!$A$6:$A$37,"Wave 1",'Outreach Queue'!$AG$6:$AG$37,"<>Skip - Closed",'Outreach Queue'!$X$6:$X$37,"Qualified") | G32: =COUNTIFS('Outreach Queue'!$D$6:$D$37,"Internal Knowledge Assistant",'Outreach Queue'!$A$6:$A$37,"Wave 1",'Outreach Queue'!$AG$6:$AG$37,"<>Skip - Closed",'Outreach Queue'!$Y$6:$Y$37,"Blueprint",'Outreach Queue'!$Z$6:$Z$37,">0") | H32: =COUNTIFS('Outreach Queue'!$D$6:$D$37,"Internal Knowledge Assistant",'Outreach Queue'!$A$6:$A$37,"Wave 1",'Outreach Queue'!$AG$6:$AG$37,"<>Skip - Closed",'Outreach Queue'!$Y$6:$Y$37,"Direct Pilot",'Outreach Queue'!$Z$6:$Z$37,">0") | I32: =COUNTIFS('Outreach Queue'!$D$6:$D$37,"Internal Knowledge Assistant",'Outreach Queue'!$A$6:$A$37,"Wave 1",'Outreach Queue'!$AG$6:$AG$37,"<>Skip - Closed",'Outreach Queue'!$AA$6:$AA$37,">0") | J32: =COUNTIFS('Outreach Queue'!$D$6:$D$37,"Internal Knowledge Assistant",'Outreach Queue'!$A$6:$A$37,"Wave 1",'Outreach Queue'!$AG$6:$AG$37,"<>Skip - Closed",'Outreach Queue'!$C$6:$C$37,"Won") | K32: =IFERROR(AVERAGEIF('Outreach Queue'!$D$6:$D$37,"Internal Knowledge Assistant",'Outreach Queue'!$G$6:$G$37),0) | L32: =IF(OR(I32>=1,F32>=2),"Promising - replicate","Unproven")
A33: Voice Agents | B33: =COUNTIF('Outreach Queue'!$D$6:$D$37,"Voice Agents") | C33: =COUNTIFS('Outreach Queue'!$D$6:$D$37,"Voice Agents",'Outreach Queue'!$A$6:$A$37,"Wave 1",'Outreach Queue'!$AG$6:$AG$37,"<>Skip - Closed",'Outreach Queue'!$AH$6:$AH$37,"<>Closed") | D33: =COUNTIFS('Outreach Queue'!$D$6:$D$37,"Voice Agents",'Outreach Queue'!$A$6:$A$37,"Wave 1",'Outreach Queue'!$AG$6:$AG$37,"<>Skip - Closed",'Outreach Queue'!$S$6:$S$37,"<>") | E33: =COUNTIFS('Outreach Queue'!$D$6:$D$37,"Voice Agents",'Outreach Queue'!$A$6:$A$37,"Wave 1",'Outreach Queue'!$AG$6:$AG$37,"<>Skip - Closed",'Outreach Queue'!$U$6:$U$37,"<>") | F33: =COUNTIFS('Outreach Queue'!$D$6:$D$37,"Voice Agents",'Outreach Queue'!$A$6:$A$37,"Wave 1",'Outreach Queue'!$AG$6:$AG$37,"<>Skip - Closed",'Outreach Queue'!$X$6:$X$37,"Qualified") | G33: =COUNTIFS('Outreach Queue'!$D$6:$D$37,"Voice Agents",'Outreach Queue'!$A$6:$A$37,"Wave 1",'Outreach Queue'!$AG$6:$AG$37,"<>Skip - Closed",'Outreach Queue'!$Y$6:$Y$37,"Blueprint",'Outreach Queue'!$Z$6:$Z$37,">0") | H33: =COUNTIFS('Outreach Queue'!$D$6:$D$37,"Voice Agents",'Outreach Queue'!$A$6:$A$37,"Wave 1",'Outreach Queue'!$AG$6:$AG$37,"<>Skip - Closed",'Outreach Queue'!$Y$6:$Y$37,"Direct Pilot",'Outreach Queue'!$Z$6:$Z$37,">0") | I33: =COUNTIFS('Outreach Queue'!$D$6:$D$37,"Voice Agents",'Outreach Queue'!$A$6:$A$37,"Wave 1",'Outreach Queue'!$AG$6:$AG$37,"<>Skip - Closed",'Outreach Queue'!$AA$6:$AA$37,">0") | J33: =COUNTIFS('Outreach Queue'!$D$6:$D$37,"Voice Agents",'Outreach Queue'!$A$6:$A$37,"Wave 1",'Outreach Queue'!$AG$6:$AG$37,"<>Skip - Closed",'Outreach Queue'!$C$6:$C$37,"Won") | K33: =IFERROR(AVERAGEIF('Outreach Queue'!$D$6:$D$37,"Voice Agents",'Outreach Queue'!$G$6:$G$37),0) | L33: =IF(OR(I33>=1,F33>=2),"Promising - replicate","Unproven")
A36: Learning-wave rule Send only to matching listings. Use the non-personal ref tag on linked rows and omit it on no-link diagnostics. Vercel Analytics records linked page views under a virtual _ref path so a verified view can be mapped back to this workbook without exposing buyer details. Wave 1 is not randomized or powered for causal lift. Rate vs sent uses the current non-closed Wave 1 maximum shown above as its planning denominator; conditional rates use observed funnel events. Two qualified replies or one funded milestone marks a category as promising, not proven. Replication and positive delivery economics are required before productizing.

Sheet Learning Wave
A1: Category presale learning wave
A3: Each page sells one defined pilot before the full product exists. Wave 1 learns offer fit and can prove category viability, but its four no-link rows cannot estimate landing-page lift.
A5: Priority | B5: Group | C5: Honest Offer | D5: Hero | E5: Pilot Boundary | F5: Target Count | G5: Wave 1 | H5: Landing Link | I5: No-Link Diagnostic | J5: Hold | K5: Landing URL | L5: Success Metrics | M5: Platform CTA | N5: Holdout Rule
A6: 1 | B6: Lead Response | C6: Packaged lead-response pilot | D6: Stop losing qualified leads between the first message and the CRM. | E6: One or two inbound channels; one CRM; one qualification policy; one booking or follow-up route; one human escalation queue; dedupe, do-not-contact logic, logs, and approval for sensitive actions. | F6: =COUNTIF('Outreach Queue'!$D$6:$D$37,"Lead Response") | G6: =COUNTIFS('Outreach Queue'!$D$6:$D$37,"Lead Response",'Outreach Queue'!$A$6:$A$37,"Wave 1") | H6: =COUNTIFS('Outreach Queue'!$D$6:$D$37,"Lead Response",'Outreach Queue'!$B$6:$B$37,"Landing Link") | I6: =COUNTIFS('Outreach Queue'!$D$6:$D$37,"Lead Response",'Outreach Queue'!$B$6:$B$37,"No-Link Diagnostic") | J6: =COUNTIFS('Outreach Queue'!$D$6:$D$37,"Lead Response",'Outreach Queue'!$C$6:$C$37,"Hold") | K6: https://dali.agents.ge/solutions/lead-response | L6: Median first-response time; complete CRM fields; qualified-to-booked conversion; scheduled follow-ups; escalation rate and reasons. | M6: Upwork: reply in the Upwork thread with CRM and primary intake channel. FL.ru: respond in the project thread with the same two inputs. | N6: Use eight Wave 1 rows, including one no-link diagnostic. Hold the two weakest or least economical rows.
A7: 2 | B7: Client Inbox | C7: Packaged client-inbox pilot | D7: Turn the shared inbox into one controlled customer-response workflow. | E7: One customer channel or tightly related channel pair; one approved answer and action policy; one CRM or case-history destination; one knowledge or file source set; one human escalation queue; logs, permissions, and approval for sensitive actions or media. | F7: =COUNTIF('Outreach Queue'!$D$6:$D$37,"Client Inbox") | G7: =COUNTIFS('Outreach Queue'!$D$6:$D$37,"Client Inbox",'Outreach Queue'!$A$6:$A$37,"Wave 1") | H7: =COUNTIFS('Outreach Queue'!$D$6:$D$37,"Client Inbox",'Outreach Queue'!$B$6:$B$37,"Landing Link") | I7: =COUNTIFS('Outreach Queue'!$D$6:$D$37,"Client Inbox",'Outreach Queue'!$B$6:$B$37,"No-Link Diagnostic") | J7: =COUNTIFS('Outreach Queue'!$D$6:$D$37,"Client Inbox",'Outreach Queue'!$C$6:$C$37,"Hold") | K7: https://dali.agents.ge/solutions/client-inbox | L7: Time to first useful response; replayed-thread acceptance; CRM or case-history write success; correct escalation; unsupported answers and unauthorized actions. | M7: Upwork: reply in the Upwork thread with the primary channel, CRM, and one representative thread. FL.ru: respond in the project thread with the same inputs and always-human actions. | N7: Use six Wave 1 rows, including one no-link diagnostic. Hold the weakest under-specified support brief.
A8: 3 | B8: Operations & Documents | C8: Packaged operations workflow pilot | D8: Turn operational documents into checked actions, not another inbox backlog. | E8: One intake source; one extraction schema; one destination system; one approval rule; one exception queue; idempotency, retries, deduplication, and an audit trail. | F8: =COUNTIF('Outreach Queue'!$D$6:$D$37,"Operations & Documents") | G8: =COUNTIFS('Outreach Queue'!$D$6:$D$37,"Operations & Documents",'Outreach Queue'!$A$6:$A$37,"Wave 1") | H8: =COUNTIFS('Outreach Queue'!$D$6:$D$37,"Operations & Documents",'Outreach Queue'!$B$6:$B$37,"Landing Link") | I8: =COUNTIFS('Outreach Queue'!$D$6:$D$37,"Operations & Documents",'Outreach Queue'!$B$6:$B$37,"No-Link Diagnostic") | J8: =COUNTIFS('Outreach Queue'!$D$6:$D$37,"Operations & Documents",'Outreach Queue'!$C$6:$C$37,"Hold") | K8: https://dali.agents.ge/solutions/operations-docs | L8: Inputs parsed without correction; exception rate; duplicate action rate; time to approved update; manual checking hours removed. | M8: Upwork: reply in the Upwork thread with one representative input and the target system. FL.ru: respond in the project thread with the same two inputs. | N8: Use six Wave 1 rows, including one no-link diagnostic. Hold the two weakest delivery or economics risks.
A9: 4 | B9: Internal Knowledge Assistant | C9: Grounded knowledge-assistant pilot | D9: Give the team answers it can verify. | E9: One team or source bundle; one permission model; one answer surface; citations; refusal on missing evidence; retrieval logs; a review set of real questions. | F9: =COUNTIF('Outreach Queue'!$D$6:$D$37,"Internal Knowledge Assistant") | G9: =COUNTIFS('Outreach Queue'!$D$6:$D$37,"Internal Knowledge Assistant",'Outreach Queue'!$A$6:$A$37,"Wave 1") | H9: =COUNTIFS('Outreach Queue'!$D$6:$D$37,"Internal Knowledge Assistant",'Outreach Queue'!$B$6:$B$37,"Landing Link") | I9: =COUNTIFS('Outreach Queue'!$D$6:$D$37,"Internal Knowledge Assistant",'Outreach Queue'!$B$6:$B$37,"No-Link Diagnostic") | J9: =COUNTIFS('Outreach Queue'!$D$6:$D$37,"Internal Knowledge Assistant",'Outreach Queue'!$C$6:$C$37,"Hold") | K9: https://dali.agents.ge/solutions/knowledge-assistant | L9: Citation coverage; grounded-answer acceptance; refusal precision; permission violations; retrieval latency; time saved. | M9: Upwork: reply in the Upwork thread with the initial source set and the users who should have access. | N9: Use four Wave 1 rows, including one no-link diagnostic. Hold the compliance-sensitive row until objections are reviewed.
A10: 5 | B10: Voice Agents | C10: Voice-agent design-partner pilot | D10: Turn one repeatable call flow into a supervised voice agent. | E10: One call type; one language; one telephony provider; one CRM; one calendar or next action; one transfer path; transcripts, summaries, latency checks, and failure routing. | F10: =COUNTIF('Outreach Queue'!$D$6:$D$37,"Voice Agents") | G10: =COUNTIFS('Outreach Queue'!$D$6:$D$37,"Voice Agents",'Outreach Queue'!$A$6:$A$37,"Wave 1") | H10: =COUNTIFS('Outreach Queue'!$D$6:$D$37,"Voice Agents",'Outreach Queue'!$B$6:$B$37,"Landing Link") | I10: =COUNTIFS('Outreach Queue'!$D$6:$D$37,"Voice Agents",'Outreach Queue'!$B$6:$B$37,"No-Link Diagnostic") | J10: =COUNTIFS('Outreach Queue'!$D$6:$D$37,"Voice Agents",'Outreach Queue'!$C$6:$C$37,"Hold") | K10: https://dali.agents.ge/solutions/voice-agents | L10: Call completion; booking or qualified handoff; transfer success; response latency; interruption recovery; transcript and CRM-note accuracy. | M10: Research only. Do not send until the four launch funnels produce objection data. | N10: Both selected Voice rows are design-partner holds and are excluded from Wave 1.
A12: Learning protocol
A13: 1. Send only to matching listings. 2. Use the tagged landing URL on Landing Link rows only and omit it on No-Link Diagnostic rows. 3. Keep every Upwork conversation inside Upwork before contract. 4. After a reply, qualify and route to paid blueprint, direct pilot, or archive. 5. Record quoted and funded amounts, objection, archive reason, delivery hours, direct cost, and gross margin. 6. Treat all variant differences as directional because allocation is small and not randomized. 7. Never pool category, platform, language, or batch. 8. Run a later 1:1 randomized test within one stratum only after a baseline reply rate exists.

Sheet Sources
A1: Sources and decision evidence
A3: Local marketplace snapshots define the selected rows. Official policy and product pages support channel rules, category language, and market packaging. URLs are plain text for auditability.
A5: Source Type | B5: Source | C5: URL | D5: Role in Decision | E5: Snapshot Date
A6: Internal snapshot | B6: Marketplace report: 158 Upwork and FL.ru listings | C6: file:///Users/dav/Desktop/reprojects/kora-v2/docs/%D0%A1%D0%B5%D0%BC/marketplace-report.html | D6: Primary listing evidence and request details | E6: 46231
A7: Internal selection | B7: Dali marketplace targets | C7: file:///Users/dav/Desktop/reprojects/kora-v2/docs/research/market/dali-marketplace-targets-2026-07-29.csv | D7: Selected 32 rows, match scores, budgets, competition, and listing URLs | E7: 46232
A8: Internal strategy | B8: Dali marketplace funnel strategy | C8: file:///Users/dav/Desktop/reprojects/kora-v2/docs/research/market/dali-marketplace-funnel-strategy-2026-07-29.md | D8: Offer architecture, pilot boundaries, metrics, and learning-wave rules | E8: 46232
A9: Internal playbook | B9: Dali marketplace sales playbook | C9: file:///Users/dav/Desktop/reprojects/kora-v2/docs/research/market/dali-marketplace-sales-playbook-2026-07-29.md | D9: Post-reply qualification, blueprint and pilot close, objections, follow-up, and archive rules | E9: 46232
A10: Agency | B10: Dali | C10: https://dali.agents.ge | D10: Current agency positioning and trust container | E10: 46232
A11: Marketplace policy | B11: Upwork: sharing files and external systems | C11: https://support.upwork.com/hc/en-us/articles/360049608113-How-to-share-documents-files-and-more-on-Upwork | D11: External scoping links are allowed, while communication rules still apply | E11: 46232
A12: Marketplace policy | B12: Upwork: pre-contract communication | C12: https://support.upwork.com/hc/en-us/articles/17995658941843--Get-to-know-each-other-before-a-contract | D12: Pre-contract communication must remain on Upwork | E12: 46232
A13: Marketplace policy | B13: Upwork: freelancer profile and portfolio | C13: https://support.upwork.com/hc/en-us/articles/360016144974-How-to-enhance-your-freelancer-profile | D13: Linked sites cannot expose off-platform contact information before contract | E13: 46232
A14: Automation market | B14: n8n pricing | C14: https://n8n.io/pricing/ | D14: Workflow-execution packaging and price language | E14: 46232
A15: Automation market | B15: Zapier pricing | C15: https://zapier.com/pricing | D15: Automation packaging benchmark | E15: 46232
A16: Automation market | B16: Make pricing | C16: https://www.make.com/en/pricing | D16: Automation packaging benchmark | E16: 46232
A17: Lead-response market | B17: Intercom pricing | C17: https://www.intercom.com/pricing | D17: Support and outcome-based agent packaging | E17: 46232
... A27: Voice market | B27: OpenAI Realtime guide | C27: https://developers.openai.com/api/docs/guides/realtime | D27: Realtime voice system capabilities and implementation context | E27: 46232
